[{"posx": 50.07678322876659, "posy": 1022.9360478549886, "radio": 30, "direccion": 360, "color": "turquoise", "entidad": 1, "velocidad": 2, "energia": -0.19999999999941115, "descanso": -0.19999999999941115, "experiencia": 100.1999999999994, "inventario": [{"posx": 1020, "posy": 856, "color": "DeepPink"}]}, {"posx": 584.0805441658792, "posy": 1019.2900136806147, "radio": 30, "direccion": 65, "color": "turquoise", "entidad": 5, "velocidad": 2, "energia": -0.19999999999941115, "descanso": -0.19999999999941115, "experiencia": 100.1999999999994, "inventario": [{"posx": 867, "posy": 629, "color": "LightGreen"}]}, {"posx": 19.179422758549983, "posy": 579.9656936099208, "radio": 30, "direccion": 322, "color": "LightGreen", "entidad": 9, "velocidad": 2, "energia": -0.19999999999941115, "descanso": -0.19999999999941115, "experiencia": 100.1999999999994, "inventario": [{"posx": 982, "posy": 427, "color": "sky blue"}]}, {"posx": 603.9137677784237, "posy": 1017.9339114546137, "radio": 30, "direccion": 227, "color": "sky blue", "entidad": 13, "velocidad": 2, "energia": -0.19999999999941115, "descanso": -0.19999999999941115, "experiencia": 100.1999999999994, "inventario": [{"posx": 425, "posy": 557, "color": "LightGreen"}]}, {"posx": 552.2762047469843, "posy": 336.6187162070777, "radio": 30, "direccion": 164, "color": "SteelBlue", "entidad": 17, "velocidad": 2, "energia": -0.19999999999941115, "descanso": -0.19999999999941115, "experiencia": 100.1999999999994, "inventario": [{"posx": 15, "posy": 763, "color": "turquoise"}]}, {"posx": 146.62573446404517, "posy": 579.0909476119965, "radio": 30, "direccion": 76.1415926535898, "color": "SteelBlue", "entidad": 21, "velocidad": 2, "energia": -0.19999999999941115, "descanso": -0.19999999999941115, "experiencia": 100.1999999999994, "inventario": [{"posx": 777, "posy": 558, "color": "DeepPink"}]}, {"posx": 635.7437341093532, "posy": 87.75110421661493, "radio": 30, "direccion": 39.1415926535898, "color": "LightGreen", "entidad": 25, "velocidad": 2, "energia": -0.19999999999941115, "descanso": -0.19999999999941115, "experiencia": 100.1999999999994, "inventario": [{"posx": 966, "posy": 506, "color": "turquoise"}]}, {"posx": 98.91791473199078, "posy": 268.1175708369536, "radio": 30, "direccion": 31.141592653589793, "color": "sky blue", "entidad": 29, "velocidad": 2, "energia": -0.19999999999941115, "descanso": -0.19999999999941115, "experiencia": 100.1999999999994, "inventario": [{"posx": 986, "posy": 555, "color": "SteelBlue"}]}, {"posx": 747.9739080246725, "posy": 453.9277472214289, "radio": 30, "direccion": 86, "color": "LightGreen", "entidad": 33, "velocidad": 2, "energia": -0.19999999999941115, "descanso": -0.19999999999941115, "experiencia": 100.1999999999994, "inventario": [{"posx": 176, "posy": 485, "color": "LightGreen"}]}, {"posx": 589.6001965852375, "posy": 59.09682404265, "radio": 30, "direccion": 338, "color": "SteelBlue", "entidad": 37, "velocidad": 2, "energia": -0.19999999999941115, "descanso": -0.19999999999941115, "experiencia": 100.1999999999994, "inventario": [{"posx": 656, "posy": 68, "color": "violet"}]}, {"posx": 297.7587025817168, "posy": 753.362154955081, "radio": 30, "direccion": 169.14159265358978, "color": "SteelBlue", "entidad": 41, "velocidad": 2, "energia": -0.19999999999941115, "descanso": -0.19999999999941115, "experiencia": 100.1999999999994, "inventario": [{"posx": 632, "posy": 377, "color": "pink"}]}, {"posx": 876.7304479133237, "posy": 71.00382923867403, "radio": 30, "direccion": 11, "color": "violet", "entidad": 45, "velocidad": 2, "energia": -0.19999999999941115, "descanso": -0.19999999999941115, "experiencia": 100.1999999999994, "inventario": [{"posx": 388, "posy": 762, "color": "turquoise"}]}, {"posx": 298.13465891534764, "posy": 891.081472782957, "radio": 30, "direccion": 19.141592653589793, "color": "DeepPink", "entidad": 49, "velocidad": 2, "energia": -0.19999999999941115, "descanso": -0.19999999999941115, "experiencia": 100.1999999999994, "inventario": [{"posx": 452, "posy": 23, "color": "violet"}]}, {"posx": 994.7930060400236, "posy": 860.6694842523535, "radio": 30, "direccion": 331.1415926535898, "color": "aquamarine", "entidad": 53, "velocidad": 2, "energia": -0.19999999999941115, "descanso": -0.19999999999941115, "experiencia": 100.1999999999994, "inventario": [{"posx": 222, "posy": 938, "color": "DeepPink"}]}, {"posx": 520.73985535051, "posy": 624.5134818990157, "radio": 30, "direccion": 54, "color": "violet", "entidad": 57, "velocidad": 2, "energia": -0.19999999999941115, "descanso": -0.19999999999941115, "experiencia": 100.1999999999994, "inventario": [{"posx": 73, "posy": 909, "color": "DeepPink"}]}, {"posx": 118.70029673518766, "posy": 864.7482956872848, "radio": 30, "direccion": 73.1415926535898, "color": "SteelBlue", "entidad": 61, "velocidad": 2, "energia": -0.19999999999941115, "descanso": -0.19999999999941115, "experiencia": 100.1999999999994, "inventario": [{"posx": 812, "posy": 408, "color": "SteelBlue"}]}, {"posx": 467.6083661589984, "posy": 735.6652156036776, "radio": 30, "direccion": 115, "color": "aquamarine", "entidad": 65, "velocidad": 2, "energia": -0.19999999999941115, "descanso": -0.19999999999941115, "experiencia": 100.1999999999994, "inventario": [{"posx": 934, "posy": 170, "color": "sky blue"}]}, {"posx": 259.02160088728624, "posy": 942.4463283205973, "radio": 30, "direccion": 30.141592653589793, "color": "violet", "entidad": 69, "velocidad": 2, "energia": -0.19999999999941115, "descanso": -0.19999999999941115, "experiencia": 100.1999999999994, "inventario": [{"posx": 125, "posy": 90, "color": "pink"}]}, {"posx": 204.2272178939607, "posy": 382.33924574743014, "radio": 30, "direccion": 40, "color": "turquoise", "entidad": 73, "velocidad": 2, "energia": -0.19999999999941115, "descanso": -0.19999999999941115, "experiencia": 100.1999999999994, "inventario": [{"posx": 230, "posy": 144, "color": "SteelBlue"}]}, {"posx": 251.8518908448185, "posy": 314.99014416037795, "radio": 30, "direccion": 242, "color": "LightGreen", "entidad": 77, "velocidad": 2, "energia": -0.19999999999941115, "descanso": -0.19999999999941115, "experiencia": 100.1999999999994, "inventario": [{"posx": 402, "posy": 811, "color": "LightGreen"}]}, {"posx": 487.51063836011235, "posy": 768.2811243476514, "radio": 30, "direccion": 266, "color": "DeepPink", "entidad": 81, "velocidad": 2, "energia": -0.19999999999941115, "descanso": -0.19999999999941115, "experiencia": 100.1999999999994, "inventario": [{"posx": 315, "posy": 955, "color": "aquamarine"}]}, {"posx": 631.3326278683113, "posy": 52.63201841864814, "radio": 30, "direccion": 170.14159265358978, "color": "SteelBlue", "entidad": 85, "velocidad": 2, "energia": -0.19999999999941115, "descanso": -0.19999999999941115, "experiencia": 100.1999999999994, "inventario": [{"posx": 924, "posy": 685, "color": "aquamarine"}]}, {"posx": 257.5031550629319, "posy": 416.7771768647932, "radio": 30, "direccion": 138.14159265358978, "color": "turquoise", "entidad": 89, "velocidad": 2, "energia": -0.19999999999941115, "descanso": -0.19999999999941115, "experiencia": 100.1999999999994, "inventario": [{"posx": 842, "posy": 790, "color": "LightGreen"}]}, {"posx": 804.2550824655766, "posy": 433.3343023763523, "radio": 30, "direccion": 205.14159265358978, "color": "aquamarine", "entidad": 93, "velocidad": 2, "energia": -0.19999999999941115, "descanso": -0.19999999999941115, "experiencia": 100.1999999999994, "inventario": [{"posx": 327, "posy": 273, "color": "sky blue"}]}, {"posx": 55.494084556054304, "posy": 425.14672419199474, "radio": 30, "direccion": 260, "color": "LightGreen", "entidad": 97, "velocidad": 2, "energia": -0.19999999999941115, "descanso": -0.19999999999941115, "experiencia": 100.1999999999994, "inventario": [{"posx": 774, "posy": 1009, "color": "violet"}]}, {"posx": 174.78376182380876, "posy": 9.438542548506273, "radio": 30, "direccion": 328.1415926535898, "color": "SteelBlue", "entidad": 101, "velocidad": 2, "energia": -0.19999999999941115, "descanso": -0.19999999999941115, "experiencia": 100.1999999999994, "inventario": [{"posx": 689, "posy": 530, "color": "DeepPink"}]}, {"posx": 491.4156384714065, "posy": 154.11913781077325, "radio": 30, "direccion": 69, "color": "DeepPink", "entidad": 105, "velocidad": 2, "energia": -0.19999999999941115, "descanso": -0.19999999999941115, "experiencia": 100.1999999999994, "inventario": [{"posx": 167, "posy": 850, "color": "turquoise"}]}, {"posx": 246.71678325502108, "posy": 678.6092424484043, "radio": 30, "direccion": 191, "color": "SteelBlue", "entidad": 109, "velocidad": 2, "energia": -0.19999999999941115, "descanso": -0.19999999999941115, "experiencia": 100.1999999999994, "inventario": [{"posx": 555, "posy": 90, "color": "violet"}]}, {"posx": 131.60717150562638, "posy": 789.9131497708013, "radio": 30, "direccion": 318.1415926535898, "color": "SteelBlue", "entidad": 113, "velocidad": 2, "energia": -0.19999999999941115, "descanso": -0.19999999999941115, "experiencia": 100.1999999999994, "inventario": [{"posx": 782, "posy": 730, "color": "SteelBlue"}]}, {"posx": 251.04555723334335, "posy": 983.1527291248896, "radio": 30, "direccion": 329, "color": "turquoise", "entidad": 117, "velocidad": 2, "energia": -0.19999999999941115, "descanso": -0.19999999999941115, "experiencia": 100.1999999999994, "inventario": [{"posx": 538, "posy": 981, "color": "sky blue"}]}, {"posx": 675.410250015259, "posy": 870.0869936608092, "radio": 30, "direccion": 332.1415926535898, "color": "violet", "entidad": 121, "velocidad": 2, "energia": -0.19999999999941115, "descanso": -0.19999999999941115, "experiencia": 100.1999999999994, "inventario": [{"posx": 930, "posy": 315, "color": "SteelBlue"}]}, {"posx": 671.5282795385842, "posy": 361.6462863254723, "radio": 30, "direccion": 212, "color": "LightGreen", "entidad": 125, "velocidad": 2, "energia": -0.19999999999941115, "descanso": -0.19999999999941115, "experiencia": 100.1999999999994, "inventario": [{"posx": 674, "posy": 166, "color": "pink"}]}, {"posx": 482.0455572333627, "posy": 613.1527291248896, "radio": 30, "direccion": 329, "color": "violet", "entidad": 129, "velocidad": 2, "energia": -0.19999999999941115, "descanso": -0.19999999999941115, "experiencia": 100.1999999999994, "inventario": [{"posx": 304, "posy": 140, "color": "DeepPink"}]}, {"posx": 714.0023793734697, "posy": 68.75118546819887, "radio": 30, "direccion": 210.14159265358978, "color": "SteelBlue", "entidad": 133, "velocidad": 2, "energia": -0.19999999999941115, "descanso": -0.19999999999941115, "experiencia": 100.1999999999994, "inventario": [{"posx": 162, "posy": 208, "color": "pink"}]}, {"posx": 873.9108421581215, "posy": 540.0893302741877, "radio": 30, "direccion": 129.14159265358978, "color": "violet", "entidad": 137, "velocidad": 2, "energia": -0.19999999999941115, "descanso": -0.19999999999941115, "experiencia": 100.1999999999994, "inventario": [{"posx": 875, "posy": 775, "color": "pink"}]}, {"posx": 309.2775973160534, "posy": 1012.7780581081261, "radio": 30, "direccion": 192.14159265358978, "color": "pink", "entidad": 141, "velocidad": 2, "energia": -0.19999999999941115, "descanso": -0.19999999999941115, "experiencia": 100.1999999999994, "inventario": [{"posx": 1003, "posy": 73, "color": "sky blue"}]}, {"posx": 702.103248833507, "posy": 667.2942032712733, "radio": 30, "direccion": 323.1415926535898, "color": "DeepPink", "entidad": 145, "velocidad": 2, "energia": -0.19999999999941115, "descanso": -0.19999999999941115, "experiencia": 100.1999999999994, "inventario": [{"posx": 732, "posy": 205, "color": "pink"}]}, {"posx": 929.4855633987776, "posy": 274.4360788184005, "radio": 30, "direccion": 63, "color": "DeepPink", "entidad": 149, "velocidad": 2, "energia": -0.19999999999941115, "descanso": -0.19999999999941115, "experiencia": 100.1999999999994, "inventario": [{"posx": 914, "posy": 301, "color": "LightGreen"}]}, {"posx": 853.7481664556174, "posy": 485.4339794349023, "radio": 30, "direccion": 323.1415926535898, "color": "sky blue", "entidad": 153, "velocidad": 2, "energia": -0.19999999999941115, "descanso": -0.19999999999941115, "experiencia": 100.1999999999994, "inventario": [{"posx": 187, "posy": 429, "color": "DeepPink"}]}, {"posx": 658.0618171493717, "posy": 692.6446680420913, "radio": 30, "direccion": 99.1415926535898, "color": "LightGreen", "entidad": 157, "velocidad": 2, "energia": -0.19999999999941115, "descanso": -0.19999999999941115, "experiencia": 100.1999999999994, "inventario": [{"posx": 495, "posy": 749, "color": "turquoise"}]}, {"posx": 546.5296564597811, "posy": 1014.5521562666603, "radio": 30, "direccion": 135, "color": "DeepPink", "entidad": 161, "velocidad": 2, "energia": -0.19999999999941115, "descanso": -0.19999999999941115, "experiencia": 100.1999999999994, "inventario": [{"posx": 391, "posy": 831, "color": "sky blue"}]}, {"posx": 333.6029610264228, "posy": 861.9990946056082, "radio": 30, "direccion": 250.14159265358978, "color": "turquoise", "entidad": 165, "velocidad": 2, "energia": -0.19999999999941115, "descanso": -0.19999999999941115, "experiencia": 100.1999999999994, "inventario": [{"posx": 779, "posy": 939, "color": "DeepPink"}]}, {"posx": 107.3604118949276, "posy": 756.7986346004375, "radio": 30, "direccion": 57.1415926535898, "color": "pink", "entidad": 169, "velocidad": 2, "energia": -0.19999999999941115, "descanso": -0.19999999999941115, "experiencia": 100.1999999999994, "inventario": [{"posx": 655, "posy": 509, "color": "pink"}]}, {"posx": 932.0017117742506, "posy": 298.3287870760509, "radio": 30, "direccion": 308, "color": "LightGreen", "entidad": 173, "velocidad": 2, "energia": -0.19999999999941115, "descanso": -0.19999999999941115, "experiencia": 100.1999999999994, "inventario": [{"posx": 999, "posy": 224, "color": "sky blue"}]}, {"posx": 1012.2265065747313, "posy": 797.7591614148464, "radio": 30, "direccion": 147.14159265358978, "color": "LightGreen", "entidad": 177, "velocidad": 2, "energia": -0.19999999999941115, "descanso": -0.19999999999941115, "experiencia": 100.1999999999994, "inventario": [{"posx": 158, "posy": 47, "color": "DeepPink"}]}, {"posx": 393.5394426389838, "posy": 810.1319562994793, "radio": 30, "direccion": 178, "color": "DeepPink", "entidad": 181, "velocidad": 2, "energia": -0.19999999999941115, "descanso": -0.19999999999941115, "experiencia": 100.1999999999994, "inventario": [{"posx": 590, "posy": 570, "color": "pink"}]}, {"posx": 610.6464583522604, "posy": 210.4504116373249, "radio": 30, "direccion": 77.1415926535898, "color": "turquoise", "entidad": 185, "velocidad": 2, "energia": -0.19999999999941115, "descanso": -0.19999999999941115, "experiencia": 100.1999999999994, "inventario": [{"posx": 542, "posy": 293, "color": "turquoise"}]}, {"posx": 640.0602208670608, "posy": 212.2287667802196, "radio": 30, "direccion": 92, "color": "sky blue", "entidad": 189, "velocidad": 2, "energia": -0.19999999999941115, "descanso": -0.19999999999941115, "experiencia": 100.1999999999994, "inventario": [{"posx": 687, "posy": 951, "color": "SteelBlue"}]}, {"posx": 652.7200101453816, "posy": 719.977275421136, "radio": 30, "direccion": 102, "color": "pink", "entidad": 193, "velocidad": 2, "energia": -0.19999999999941115, "descanso": -0.19999999999941115, "experiencia": 100.1999999999994, "inventario": [{"posx": 584, "posy": 247, "color": "pink"}]}, {"posx": 732.2943301819812, "posy": 997.810111342045, "radio": 30, "direccion": 149.14159265358978, "color": "DeepPink", "entidad": 197, "velocidad": 2, "energia": -0.19999999999941115, "descanso": -0.19999999999941115, "experiencia": 100.1999999999994, "inventario": [{"posx": 177, "posy": 320, "color": "violet"}]}, {"posx": 4.350956686377637, "posy": 413.02409815069535, "radio": 30, "direccion": 308.1415926535898, "color": "LightGreen", "entidad": 201, "velocidad": 2, "energia": -0.19999999999941115, "descanso": -0.19999999999941115, "experiencia": 100.1999999999994, "inventario": [{"posx": 942, "posy": 711, "color": "turquoise"}]}, {"posx": 457.58571460963924, "posy": 315.10742929291627, "radio": 30, "direccion": 286, "color": "SteelBlue", "entidad": 205, "velocidad": 2, "energia": -0.19999999999941115, "descanso": -0.19999999999941115, "experiencia": 100.1999999999994, "inventario": [{"posx": 65, "posy": 663, "color": "pink"}]}, {"posx": 161.4166748525635, "posy": 734.7477851671246, "radio": 30, "direccion": 277.1415926535898, "color": "violet", "entidad": 209, "velocidad": 2, "energia": -0.19999999999941115, "descanso": -0.19999999999941115, "experiencia": 100.1999999999994, "inventario": [{"posx": 7, "posy": 561, "color": "DeepPink"}]}, {"posx": 101.96202607220565, "posy": 962.2625455014448, "radio": 30, "direccion": 15, "color": "sky blue", "entidad": 213, "velocidad": 2, "energia": -0.19999999999941115, "descanso": -0.19999999999941115, "experiencia": 100.1999999999994, "inventario": [{"posx": 492, "posy": 228, "color": "sky blue"}]}, {"posx": 210.50517121415407, "posy": 646.9603835932339, "radio": 30, "direccion": 111, "color": "SteelBlue", "entidad": 217, "velocidad": 2, "energia": -0.19999999999941115, "descanso": -0.19999999999941115, "experiencia": 100.1999999999994, "inventario": [{"posx": 779, "posy": 505, "color": "aquamarine"}]}, {"posx": 142.73069085033967, "posy": 127.36756846328439, "radio": 30, "direccion": 318, "color": "LightGreen", "entidad": 221, "velocidad": 2, "energia": -0.19999999999941115, "descanso": -0.19999999999941115, "experiencia": 100.1999999999994, "inventario": [{"posx": 11, "posy": 754, "color": "pink"}]}, {"posx": 103.83785925231108, "posy": 535.1323546675987, "radio": 30, "direccion": 21, "color": "sky blue", "entidad": 225, "velocidad": 2, "energia": -0.19999999999941115, "descanso": -0.19999999999941115, "experiencia": 100.1999999999994, "inventario": [{"posx": 680, "posy": 54, "color": "aquamarine"}]}, {"posx": 697.4297601050425, "posy": 985.978677533755, "radio": 30, "direccion": 317.1415926535898, "color": "SteelBlue", "entidad": 229, "velocidad": 2, "energia": -0.19999999999941115, "descanso": -0.19999999999941115, "experiencia": 100.1999999999994, "inventario": [{"posx": 586, "posy": 672, "color": "violet"}]}, {"posx": 423.3335538624712, "posy": 1015.27603818528, "radio": 30, "direccion": 215, "color": "aquamarine", "entidad": 233, "velocidad": 2, "energia": -0.19999999999941115, "descanso": -0.19999999999941115, "experiencia": 100.1999999999994, "inventario": [{"posx": 863, "posy": 836, "color": "sky blue"}]}, {"posx": 227.36022186203985, "posy": 304.0954665986594, "radio": 30, "direccion": 300, "color": "pink", "entidad": 237, "velocidad": 2, "energia": -0.19999999999941115, "descanso": -0.19999999999941115, "experiencia": 100.1999999999994, "inventario": [{"posx": 524, "posy": 752, "color": "violet"}]}, {"posx": 364.71776643311097, "posy": 980.7733093939636, "radio": 30, "direccion": 303, "color": "violet", "entidad": 241, "velocidad": 2, "energia": -0.19999999999941115, "descanso": -0.19999999999941115, "experiencia": 100.1999999999994, "inventario": [{"posx": 714, "posy": 583, "color": "DeepPink"}]}, {"posx": 934.0586123679623, "posy": 598.1064736821335, "radio": 30, "direccion": 94, "color": "SteelBlue", "entidad": 245, "velocidad": 2, "energia": -0.19999999999941115, "descanso": -0.19999999999941115, "experiencia": 100.1999999999994, "inventario": [{"posx": 482, "posy": 504, "color": "SteelBlue"}]}, {"posx": 404.9442784525931, "posy": 304.09504724895675, "radio": 30, "direccion": 261, "color": "pink", "entidad": 249, "velocidad": 2, "energia": -0.19999999999941115, "descanso": -0.19999999999941115, "experiencia": 100.1999999999994, "inventario": [{"posx": 199, "posy": 656, "color": "aquamarine"}]}, {"posx": 105.72903838077697, "posy": 956.6690859145149, "radio": 30, "direccion": 307.1415926535898, "color": "aquamarine", "entidad": 253, "velocidad": 2, "energia": -0.19999999999941115, "descanso": -0.19999999999941115, "experiencia": 100.1999999999994, "inventario": [{"posx": 465, "posy": 434, "color": "aquamarine"}]}, {"posx": 618.9605028689629, "posy": 178.76953296915553, "radio": 30, "direccion": 312, "color": "violet", "entidad": 257, "velocidad": 2, "energia": -0.19999999999941115, "descanso": -0.19999999999941115, "experiencia": 100.1999999999994, "inventario": [{"posx": 205, "posy": 563, "color": "turquoise"}]}, {"posx": 130.1146222942036, "posy": 502.2216827634526, "radio": 30, "direccion": 93, "color": "LightGreen", "entidad": 261, "velocidad": 2, "energia": -0.19999999999941115, "descanso": -0.19999999999941115, "experiencia": 100.1999999999994, "inventario": [{"posx": 549, "posy": 709, "color": "DeepPink"}]}, {"posx": 681.2839198377229, "posy": 145.01171869256348, "radio": 30, "direccion": 112, "color": "turquoise", "entidad": 265, "velocidad": 2, "energia": -0.19999999999941115, "descanso": -0.19999999999941115, "experiencia": 100.1999999999994, "inventario": [{"posx": 377, "posy": 631, "color": "turquoise"}]}, {"posx": 695.2197192001256, "posy": 236.53625351016842, "radio": 30, "direccion": 210.14159265358978, "color": "aquamarine", "entidad": 269, "velocidad": 2, "energia": -0.19999999999941115, "descanso": -0.19999999999941115, "experiencia": 100.1999999999994, "inventario": [{"posx": 223, "posy": 495, "color": "SteelBlue"}]}, {"posx": 617.8965546347812, "posy": 49.2179415768818, "radio": 30, "direccion": 262, "color": "aquamarine", "entidad": 273, "velocidad": 2, "energia": -0.19999999999941115, "descanso": -0.19999999999941115, "experiencia": 100.1999999999994, "inventario": [{"posx": 356, "posy": 366, "color": "turquoise"}]}, {"posx": 657.0270889060829, "posy": 459.676308669147, "radio": 30, "direccion": 41.1415926535898, "color": "turquoise", "entidad": 277, "velocidad": 2, "energia": -0.19999999999941115, "descanso": -0.19999999999941115, "experiencia": 100.1999999999994, "inventario": [{"posx": 794, "posy": 366, "color": "DeepPink"}]}, {"posx": 386.05660025914733, "posy": 345.7600343344407, "radio": 30, "direccion": 259.1415926535898, "color": "turquoise", "entidad": 281, "velocidad": 2, "energia": -0.19999999999941115, "descanso": -0.19999999999941115, "experiencia": 100.1999999999994, "inventario": [{"posx": 247, "posy": 302, "color": "violet"}]}, {"posx": 747.4580751624901, "posy": 369.49779103642703, "radio": 30, "direccion": 288, "color": "turquoise", "entidad": 285, "velocidad": 2, "energia": -0.19999999999941115, "descanso": -0.19999999999941115, "experiencia": 100.1999999999994, "inventario": [{"posx": 539, "posy": 988, "color": "LightGreen"}]}, {"posx": 942.5991445594645, "posy": 450.91580098777047, "radio": 30, "direccion": 197.14159265358978, "color": "SteelBlue", "entidad": 289, "velocidad": 2, "energia": -0.19999999999941115, "descanso": -0.19999999999941115, "experiencia": 100.1999999999994, "inventario": [{"posx": 205, "posy": 529, "color": "sky blue"}]}, {"posx": 510.13145041392517, "posy": 920.1593591526575, "radio": 30, "direccion": 238.14159265358978, "color": "LightGreen", "entidad": 293, "velocidad": 2, "energia": -0.19999999999941115, "descanso": -0.19999999999941115, "experiencia": 100.1999999999994, "inventario": [{"posx": 374, "posy": 935, "color": "pink"}]}, {"posx": 332.60019658523436, "posy": 524.096824042649, "radio": 30, "direccion": 338, "color": "turquoise", "entidad": 297, "velocidad": 2, "energia": -0.19999999999941115, "descanso": -0.19999999999941115, "experiencia": 100.1999999999994, "inventario": [{"posx": 662, "posy": 13, "color": "turquoise"}]}, {"posx": 756.5600861690349, "posy": 561.9615930344943, "radio": 30, "direccion": 20, "color": "SteelBlue", "entidad": 301, "velocidad": 2, "energia": -0.19999999999941115, "descanso": -0.19999999999941115, "experiencia": 100.1999999999994, "inventario": [{"posx": 886, "posy": 589, "color": "LightGreen"}]}, {"posx": 67.35071841085136, "posy": 134.76092752906817, "radio": 30, "direccion": 64.1415926535898, "color": "SteelBlue", "entidad": 305, "velocidad": 2, "energia": -0.19999999999941115, "descanso": -0.19999999999941115, "experiencia": 100.1999999999994, "inventario": [{"posx": 681, "posy": 491, "color": "violet"}]}, {"posx": 653.002112998375, "posy": 636.7493194280676, "radio": 30, "direccion": 180, "color": "turquoise", "entidad": 309, "velocidad": 2, "energia": -0.19999999999941115, "descanso": -0.19999999999941115, "experiencia": 100.1999999999994, "inventario": [{"posx": 963, "posy": 515, "color": "SteelBlue"}]}, {"posx": 464.5736166103228, "posy": 1018.7551530896853, "radio": 30, "direccion": 186.14159265358978, "color": "DeepPink", "entidad": 313, "velocidad": 2, "energia": -0.19999999999941115, "descanso": -0.19999999999941115, "experiencia": 100.1999999999994, "inventario": [{"posx": 794, "posy": 994, "color": "turquoise"}]}, {"posx": 101.04555723334994, "posy": 631.1527291248896, "radio": 30, "direccion": 329, "color": "SteelBlue", "entidad": 317, "velocidad": 2, "energia": -0.19999999999941115, "descanso": -0.19999999999941115, "experiencia": 100.1999999999994, "inventario": [{"posx": 293, "posy": 221, "color": "sky blue"}]}, {"posx": 782.955295146726, "posy": 51.46054931343018, "radio": 30, "direccion": 296.1415926535898, "color": "aquamarine", "entidad": 321, "velocidad": 2, "energia": -0.19999999999941115, "descanso": -0.19999999999941115, "experiencia": 100.1999999999994, "inventario": [{"posx": 826, "posy": 291, "color": "pink"}]}, {"posx": 189.71599798288264, "posy": 297.82710639320106, "radio": 30, "direccion": 175.14159265358978, "color": "violet", "entidad": 325, "velocidad": 2, "energia": -0.19999999999941115, "descanso": -0.19999999999941115, "experiencia": 100.1999999999994, "inventario": [{"posx": 932, "posy": 263, "color": "sky blue"}]}, {"posx": 1020.8337560107809, "posy": 388.1769631915936, "radio": 30, "direccion": 33.1415926535898, "color": "pink", "entidad": 329, "velocidad": 2, "energia": -0.19999999999941115, "descanso": -0.19999999999941115, "experiencia": 100.1999999999994, "inventario": [{"posx": 591, "posy": 898, "color": "pink"}]}, {"posx": 831.6057418395416, "posy": 87.64007476498637, "radio": 30, "direccion": 42, "color": "pink", "entidad": 333, "velocidad": 2, "energia": -0.19999999999941115, "descanso": -0.19999999999941115, "experiencia": 100.1999999999994, "inventario": [{"posx": 632, "posy": 737, "color": "turquoise"}]}, {"posx": 286.77460779627654, "posy": 645.2456403634374, "radio": 30, "direccion": 104, "color": "SteelBlue", "entidad": 337, "velocidad": 2, "energia": -0.19999999999941115, "descanso": -0.19999999999941115, "experiencia": 100.1999999999994, "inventario": [{"posx": 431, "posy": 16, "color": "DeepPink"}]}, {"posx": 57.507632816442246, "posy": 923.9645607913941, "radio": 30, "direccion": 59, "color": "sky blue", "entidad": 341, "velocidad": 2, "energia": -0.19999999999941115, "descanso": -0.19999999999941115, "experiencia": 100.1999999999994, "inventario": [{"posx": 825, "posy": 546, "color": "violet"}]}, {"posx": 89.64291227892046, "posy": 755.3966032358351, "radio": 30, "direccion": 134, "color": "violet", "entidad": 345, "velocidad": 2, "energia": -0.19999999999941115, "descanso": -0.19999999999941115, "experiencia": 100.1999999999994, "inventario": [{"posx": 181, "posy": 700, "color": "turquoise"}]}, {"posx": 423.34475947588083, "posy": 468.0189730270203, "radio": 30, "direccion": 120, "color": "violet", "entidad": 349, "velocidad": 2, "energia": -0.19999999999941115, "descanso": -0.19999999999941115, "experiencia": 100.1999999999994, "inventario": [{"posx": 493, "posy": 813, "color": "LightGreen"}]}, {"posx": 870.893342697306, "posy": 307.16603492975304, "radio": 30, "direccion": 270, "color": "turquoise", "entidad": 353, "velocidad": 2, "energia": -0.19999999999941115, "descanso": -0.19999999999941115, "experiencia": 100.1999999999994, "inventario": [{"posx": 286, "posy": 1016, "color": "pink"}]}, {"posx": 1003.7739040871621, "posy": 561.7420827867384, "radio": 30, "direccion": 101, "color": "DeepPink", "entidad": 357, "velocidad": 2, "energia": -0.19999999999941115, "descanso": -0.19999999999941115, "experiencia": 100.1999999999994, "inventario": [{"posx": 776, "posy": 278, "color": "LightGreen"}]}, {"posx": 548.0586123679623, "posy": 135.10647368214458, "radio": 30, "direccion": 94, "color": "violet", "entidad": 361, "velocidad": 2, "energia": -0.19999999999941115, "descanso": -0.19999999999941115, "experiencia": 100.1999999999994, "inventario": [{"posx": 658, "posy": 27, "color": "DeepPink"}]}, {"posx": 787.7188667556095, "posy": 868.6033873614736, "radio": 30, "direccion": 229.14159265358978, "color": "SteelBlue", "entidad": 365, "velocidad": 2, "energia": -0.19999999999941115, "descanso": -0.19999999999941115, "experiencia": 100.1999999999994, "inventario": [{"posx": 733, "posy": 316, "color": "LightGreen"}]}, {"posx": 435.97390802466117, "posy": 460.9277472214293, "radio": 30, "direccion": 86, "color": "pink", "entidad": 369, "velocidad": 2, "energia": -0.19999999999941115, "descanso": -0.19999999999941115, "experiencia": 100.1999999999994, "inventario": [{"posx": 632, "posy": 559, "color": "turquoise"}]}, {"posx": 24.002112998375445, "posy": 296.74931942806757, "radio": 30, "direccion": 180, "color": "DeepPink", "entidad": 373, "velocidad": 2, "energia": -0.19999999999941115, "descanso": -0.19999999999941115, "experiencia": 100.1999999999994, "inventario": [{"posx": 666, "posy": 950, "color": "DeepPink"}]}, {"posx": 415.02012284791476, "posy": 106.6641243074122, "radio": 30, "direccion": 176, "color": "sky blue", "entidad": 377, "velocidad": 2, "energia": -0.19999999999941115, "descanso": -0.19999999999941115, "experiencia": 100.1999999999994, "inventario": [{"posx": 849, "posy": 899, "color": "violet"}]}, {"posx": 958.6278084067551, "posy": 714.5912564891283, "radio": 30, "direccion": 70, "color": "pink", "entidad": 381, "velocidad": 2, "energia": -0.19999999999941115, "descanso": -0.19999999999941115, "experiencia": 100.1999999999994, "inventario": [{"posx": 456, "posy": 842, "color": "DeepPink"}]}, {"posx": 5.726570125005891, "posy": 475.0063445971796, "radio": 30, "direccion": 243, "color": "sky blue", "entidad": 385, "velocidad": 2, "energia": -0.19999999999941115, "descanso": -0.19999999999941115, "experiencia": 100.1999999999994, "inventario": [{"posx": 462, "posy": 345, "color": "violet"}]}, {"posx": 602.7739040871622, "posy": 684.7420827867538, "radio": 30, "direccion": 101, "color": "sky blue", "entidad": 389, "velocidad": 2, "energia": -0.19999999999941115, "descanso": -0.19999999999941115, "experiencia": 100.1999999999994, "inventario": [{"posx": 435, "posy": 843, "color": "aquamarine"}]}, {"posx": 926.5200265279549, "posy": 622.8553859480148, "radio": 30, "direccion": 311.1415926535898, "color": "SteelBlue", "entidad": 393, "velocidad": 2, "energia": -0.19999999999941115, "descanso": -0.19999999999941115, "experiencia": 100.1999999999994, "inventario": [{"posx": 700, "posy": 362, "color": "turquoise"}]}, {"posx": 883.6711261585629, "posy": 739.3477448669953, "radio": 30, "direccion": 317.1415926535898, "color": "LightGreen", "entidad": 397, "velocidad": 2, "energia": -0.19999999999941115, "descanso": -0.19999999999941115, "experiencia": 100.1999999999994, "inventario": [{"posx": 353, "posy": 579, "color": "pink"}]}, {"posx": 904.0995064433316, "posy": 970.30686900447, "radio": 30, "direccion": 4.141592653589793, "color": "DeepPink", "entidad": 401, "velocidad": 2, "energia": -0.19999999999941115, "descanso": -0.19999999999941115, "experiencia": 100.1999999999994, "inventario": [{"posx": 988, "posy": 191, "color": "sky blue"}]}, {"posx": 139.57884332080496, "posy": 526.835405164809, "radio": 30, "direccion": 294.1415926535898, "color": "sky blue", "entidad": 405, "velocidad": 2, "energia": -0.19999999999941115, "descanso": -0.19999999999941115, "experiencia": 100.1999999999994, "inventario": [{"posx": 570, "posy": 502, "color": "SteelBlue"}]}, {"posx": 49.56019106618982, "posy": 731.9815383667986, "radio": 30, "direccion": 265.1415926535898, "color": "pink", "entidad": 409, "velocidad": 2, "energia": -0.19999999999941115, "descanso": -0.19999999999941115, "experiencia": 100.1999999999994, "inventario": [{"posx": 191, "posy": 313, "color": "violet"}]}, {"posx": 210.99683156198626, "posy": 253.31709099338403, "radio": 30, "direccion": 47, "color": "pink", "entidad": 413, "velocidad": 2, "energia": -0.19999999999941115, "descanso": -0.19999999999941115, "experiencia": 100.1999999999994, "inventario": [{"posx": 370, "posy": 820, "color": "pink"}]}, {"posx": 767.9146616549167, "posy": 614.9050892897104, "radio": 30, "direccion": 287, "color": "pink", "entidad": 417, "velocidad": 2, "energia": -0.19999999999941115, "descanso": -0.19999999999941115, "experiencia": 100.1999999999994, "inventario": [{"posx": 924, "posy": 724, "color": "turquoise"}]}, {"posx": 331.08226034814027, "posy": 377.2479519267174, "radio": 30, "direccion": 61, "color": "LightGreen", "entidad": 421, "velocidad": 2, "energia": -0.19999999999941115, "descanso": -0.19999999999941115, "experiencia": 100.1999999999994, "inventario": [{"posx": 563, "posy": 822, "color": "SteelBlue"}]}, {"posx": 795.6007499901735, "posy": 843.4616011857979, "radio": 30, "direccion": 74.1415926535898, "color": "pink", "entidad": 425, "velocidad": 2, "energia": -0.19999999999941115, "descanso": -0.19999999999941115, "experiencia": 100.1999999999994, "inventario": [{"posx": 658, "posy": 775, "color": "LightGreen"}]}, {"posx": 689.8087918358003, "posy": 800.9655373019555, "radio": 30, "direccion": 33, "color": "aquamarine", "entidad": 429, "velocidad": 2, "energia": -0.19999999999941115, "descanso": -0.19999999999941115, "experiencia": 100.1999999999994, "inventario": [{"posx": 873, "posy": 119, "color": "violet"}]}, {"posx": 76.52893869705736, "posy": 583.7952760262019, "radio": 30, "direccion": 160, "color": "DeepPink", "entidad": 433, "velocidad": 2, "energia": -0.19999999999941115, "descanso": -0.19999999999941115, "experiencia": 100.1999999999994, "inventario": [{"posx": 11, "posy": 191, "color": "aquamarine"}]}, {"posx": 648.6563478092281, "posy": 498.58057622702484, "radio": 30, "direccion": 35, "color": "SteelBlue", "entidad": 437, "velocidad": 2, "energia": -0.19999999999941115, "descanso": -0.19999999999941115, "experiencia": 100.1999999999994, "inventario": [{"posx": 986, "posy": 101, "color": "sky blue"}]}, {"posx": 593.1492547609012, "posy": 267.00187479576107, "radio": 30, "direccion": 113, "color": "violet", "entidad": 441, "velocidad": 2, "energia": -0.19999999999941115, "descanso": -0.19999999999941115, "experiencia": 100.1999999999994, "inventario": [{"posx": 201, "posy": 927, "color": "DeepPink"}]}, {"posx": 983.013866844061, "posy": 867.9207255002934, "radio": 30, "direccion": 294.1415926535898, "color": "aquamarine", "entidad": 445, "velocidad": 2, "energia": -0.19999999999941115, "descanso": -0.19999999999941115, "experiencia": 100.1999999999994, "inventario": [{"posx": 311, "posy": 820, "color": "sky blue"}]}, {"posx": 28.86783155634339, "posy": 157.78370867809306, "radio": 30, "direccion": 304.1415926535898, "color": "SteelBlue", "entidad": 449, "velocidad": 2, "energia": -0.19999999999941115, "descanso": -0.19999999999941115, "experiencia": 100.1999999999994, "inventario": [{"posx": 263, "posy": 766, "color": "turquoise"}]}, {"posx": 572.1225321853295, "posy": 926.0530570441774, "radio": 30, "direccion": 324.1415926535898, "color": "violet", "entidad": 453, "velocidad": 2, "energia": -0.19999999999941115, "descanso": -0.19999999999941115, "experiencia": 100.1999999999994, "inventario": [{"posx": 318, "posy": 85, "color": "DeepPink"}]}, {"posx": 433.55200828231705, "posy": 170.49168822064593, "radio": 30, "direccion": 67, "color": "aquamarine", "entidad": 457, "velocidad": 2, "energia": -0.19999999999941115, "descanso": -0.19999999999941115, "experiencia": 100.1999999999994, "inventario": [{"posx": 623, "posy": 423, "color": "DeepPink"}]}, {"posx": 22.966197355684113, "posy": 368.2144683037531, "radio": 30, "direccion": 36, "color": "DeepPink", "entidad": 461, "velocidad": 2, "energia": -0.19999999999941115, "descanso": -0.19999999999941115, "experiencia": 100.1999999999994, "inventario": [{"posx": 986, "posy": 406, "color": "sky blue"}]}, {"posx": 741.8166771073783, "posy": 550.8660115320204, "radio": 30, "direccion": 284, "color": "SteelBlue", "entidad": 465, "velocidad": 2, "energia": -0.19999999999941115, "descanso": -0.19999999999941115, "experiencia": 100.1999999999994, "inventario": [{"posx": 623, "posy": 784, "color": "sky blue"}]}, {"posx": 494.6211062714066, "posy": 131.9241632283774, "radio": 30, "direccion": 28, "color": "aquamarine", "entidad": 469, "velocidad": 2, "energia": -0.19999999999941115, "descanso": -0.19999999999941115, "experiencia": 100.1999999999994, "inventario": [{"posx": 744, "posy": 512, "color": "LightGreen"}]}, {"posx": 920.7092179294266, "posy": 786.6118903361678, "radio": 30, "direccion": 263.1415926535898, "color": "turquoise", "entidad": 473, "velocidad": 2, "energia": -0.19999999999941115, "descanso": -0.19999999999941115, "experiencia": 100.1999999999994, "inventario": [{"posx": 74, "posy": 807, "color": "aquamarine"}]}, {"posx": 280.70070042076736, "posy": 4.970252669092467, "radio": 30, "direccion": 153.28318530717956, "color": "aquamarine", "entidad": 477, "velocidad": 2, "energia": -0.19999999999941115, "descanso": -0.19999999999941115, "experiencia": 100.1999999999994, "inventario": [{"posx": 855, "posy": 40, "color": "DeepPink"}]}, {"posx": 684.2120087895523, "posy": 449.6180517380618, "radio": 30, "direccion": 169, "color": "violet", "entidad": 481, "velocidad": 2, "energia": -0.19999999999941115, "descanso": -0.19999999999941115, "experiencia": 100.1999999999994, "inventario": [{"posx": 30, "posy": 145, "color": "DeepPink"}]}, {"posx": 795.4642523192604, "posy": 541.327476076693, "radio": 30, "direccion": 14, "color": "turquoise", "entidad": 485, "velocidad": 2, "energia": -0.19999999999941115, "descanso": -0.19999999999941115, "experiencia": 100.1999999999994, "inventario": [{"posx": 718, "posy": 349, "color": "DeepPink"}]}, {"posx": 152.47567965278398, "posy": 85.98624987747706, "radio": 30, "direccion": 216.14159265358978, "color": "SteelBlue", "entidad": 489, "velocidad": 2, "energia": -0.19999999999941115, "descanso": -0.19999999999941115, "experiencia": 100.1999999999994, "inventario": [{"posx": 508, "posy": 319, "color": "pink"}]}, {"posx": 908.4792245721876, "posy": 763.2871376726857, "radio": 30, "direccion": 89, "color": "LightGreen", "entidad": 493, "velocidad": 2, "energia": -0.19999999999941115, "descanso": -0.19999999999941115, "experiencia": 100.1999999999994, "inventario": [{"posx": 724, "posy": 354, "color": "LightGreen"}]}, {"posx": 131.13074137706403, "posy": 872.38037293714, "radio": 30, "direccion": 334.1415926535898, "color": "pink", "entidad": 497, "velocidad": 2, "energia": -0.19999999999941115, "descanso": -0.19999999999941115, "experiencia": 100.1999999999994, "inventario": [{"posx": 1004, "posy": 131, "color": "violet"}]}, {"posx": 722.3309079674101, "posy": 755.8469808141859, "radio": 30, "direccion": 293.1415926535898, "color": "violet", "entidad": 501, "velocidad": 2, "energia": -0.19999999999941115, "descanso": -0.19999999999941115, "experiencia": 100.1999999999994, "inventario": [{"posx": 478, "posy": 398, "color": "pink"}]}, {"posx": 755.7177664331332, "posy": 649.7733093939636, "radio": 30, "direccion": 303, "color": "sky blue", "entidad": 505, "velocidad": 2, "energia": -0.19999999999941115, "descanso": -0.19999999999941115, "experiencia": 100.1999999999994, "inventario": [{"posx": 739, "posy": 859, "color": "turquoise"}]}, {"posx": 690.4337948224844, "posy": 251.88011427536625, "radio": 30, "direccion": 38, "color": "violet", "entidad": 509, "velocidad": 2, "energia": -0.19999999999941115, "descanso": -0.19999999999941115, "experiencia": 100.1999999999994, "inventario": [{"posx": 950, "posy": 656, "color": "sky blue"}]}, {"posx": 561.4502137848925, "posy": 987.1376070208395, "radio": 30, "direccion": 177, "color": "DeepPink", "entidad": 513, "velocidad": 2, "energia": -0.19999999999941115, "descanso": -0.19999999999941115, "experiencia": 100.1999999999994, "inventario": [{"posx": 925, "posy": 518, "color": "LightGreen"}]}, {"posx": 485.9262416298304, "posy": 336.43542232739503, "radio": 30, "direccion": 221.14159265358978, "color": "pink", "entidad": 517, "velocidad": 2, "energia": -0.19999999999941115, "descanso": -0.19999999999941115, "experiencia": 100.1999999999994, "inventario": [{"posx": 691, "posy": 330, "color": "pink"}]}, {"posx": 891.0, "posy": 610.0, "radio": 30, "direccion": 0, "color": "sky blue", "entidad": 521, "velocidad": 2, "energia": -0.19999999999941115, "descanso": -0.19999999999941115, "experiencia": 100.1999999999994, "inventario": [{"posx": 461, "posy": 973, "color": "LightGreen"}]}, {"posx": 260.0022114404286, "posy": 209.33223025463136, "radio": 30, "direccion": 121.1415926535898, "color": "turquoise", "entidad": 525, "velocidad": 2, "energia": -0.19999999999941115, "descanso": -0.19999999999941115, "experiencia": 100.1999999999994, "inventario": [{"posx": 841, "posy": 484, "color": "DeepPink"}]}, {"posx": 239.51567792943356, "posy": 347.94783607615625, "radio": 30, "direccion": 219, "color": "violet", "entidad": 529, "velocidad": 2, "energia": -0.19999999999941115, "descanso": -0.19999999999941115, "experiencia": 100.1999999999994, "inventario": [{"posx": 888, "posy": 422, "color": "LightGreen"}]}, {"posx": 551.3589168981855, "posy": 12.828543505970691, "radio": 30, "direccion": 354.1415926535898, "color": "aquamarine", "entidad": 533, "velocidad": 2, "energia": -0.19999999999941115, "descanso": -0.19999999999941115, "experiencia": 100.1999999999994, "inventario": [{"posx": 750, "posy": 501, "color": "LightGreen"}]}, {"posx": 783.2667306369636, "posy": 643.5232566106782, "radio": 30, "direccion": 301, "color": "sky blue", "entidad": 537, "velocidad": 2, "energia": -0.19999999999941115, "descanso": -0.19999999999941115, "experiencia": 100.1999999999994, "inventario": [{"posx": 629, "posy": 16, "color": "LightGreen"}]}, {"posx": 768.8042377478712, "posy": 258.8962273835911, "radio": 30, "direccion": 183.14159265358978, "color": "violet", "entidad": 541, "velocidad": 2, "energia": -0.19999999999941115, "descanso": -0.19999999999941115, "experiencia": 100.1999999999994, "inventario": [{"posx": 80, "posy": 18, "color": "turquoise"}]}, {"posx": 584.8333286173676, "posy": 295.6160114490836, "radio": 30, "direccion": 266.1415926535898, "color": "aquamarine", "entidad": 545, "velocidad": 2, "energia": -0.19999999999941115, "descanso": -0.19999999999941115, "experiencia": 100.1999999999994, "inventario": [{"posx": 855, "posy": 955, "color": "sky blue"}]}, {"posx": 73.73188055244465, "posy": 910.0087866685406, "radio": 30, "direccion": 354, "color": "SteelBlue", "entidad": 549, "velocidad": 2, "energia": -0.19999999999941115, "descanso": -0.19999999999941115, "experiencia": 100.1999999999994, "inventario": [{"posx": 649, "posy": 462, "color": "sky blue"}]}, {"posx": 421.87013074409356, "posy": 616.8057883953924, "radio": 30, "direccion": 281, "color": "DeepPink", "entidad": 553, "velocidad": 2, "energia": -0.19999999999941115, "descanso": -0.19999999999941115, "experiencia": 100.1999999999994, "inventario": [{"posx": 205, "posy": 841, "color": "sky blue"}]}, {"posx": 950.232559510647, "posy": 660.9273319744013, "radio": 30, "direccion": 114, "color": "aquamarine", "entidad": 557, "velocidad": 2, "energia": -0.19999999999941115, "descanso": -0.19999999999941115, "experiencia": 100.1999999999994, "inventario": [{"posx": 432, "posy": 437, "color": "LightGreen"}]}, {"posx": 794.6993284989578, "posy": 290.67781707941543, "radio": 30, "direccion": 325, "color": "turquoise", "entidad": 561, "velocidad": 2, "energia": -0.19999999999941115, "descanso": -0.19999999999941115, "experiencia": 100.1999999999994, "inventario": [{"posx": 576, "posy": 295, "color": "aquamarine"}]}, {"posx": 18.00416995234866, "posy": 126.5362470345922, "radio": 30, "direccion": 290.1415926535898, "color": "LightGreen", "entidad": 565, "velocidad": 2, "energia": -0.19999999999941115, "descanso": -0.19999999999941115, "experiencia": 100.1999999999994, "inventario": [{"posx": 870, "posy": 1007, "color": "pink"}]}, {"posx": 770.2406014879277, "posy": 121.10263158597026, "radio": 30, "direccion": 241.14159265358978, "color": "turquoise", "entidad": 569, "velocidad": 2, "energia": -0.19999999999941115, "descanso": -0.19999999999941115, "experiencia": 100.1999999999994, "inventario": [{"posx": 6, "posy": 511, "color": "violet"}]}, {"posx": 595.5020582004031, "posy": 318.93920413538586, "radio": 30, "direccion": 303.1415926535898, "color": "DeepPink", "entidad": 573, "velocidad": 2, "energia": -0.19999999999941115, "descanso": -0.19999999999941115, "experiencia": 100.1999999999994, "inventario": [{"posx": 961, "posy": 710, "color": "sky blue"}]}, {"posx": 715.0622578927905, "posy": 843.1387362648969, "radio": 30, "direccion": 165, "color": "pink", "entidad": 577, "velocidad": 2, "energia": -0.19999999999941115, "descanso": -0.19999999999941115, "experiencia": 100.1999999999994, "inventario": [{"posx": 740, "posy": 423, "color": "aquamarine"}]}, {"posx": 482.18335633970446, "posy": 846.2746157555755, "radio": 30, "direccion": 342, "color": "DeepPink", "entidad": 581, "velocidad": 2, "energia": -0.19999999999941115, "descanso": -0.19999999999941115, "experiencia": 100.1999999999994, "inventario": [{"posx": 808, "posy": 162, "color": "sky blue"}]}, {"posx": 958.5672804298883, "posy": 176.15958148510023, "radio": 30, "direccion": 127.1415926535898, "color": "DeepPink", "entidad": 585, "velocidad": 2, "energia": -0.19999999999941115, "descanso": -0.19999999999941115, "experiencia": 100.1999999999994, "inventario": [{"posx": 774, "posy": 79, "color": "violet"}]}, {"posx": 828.8593294296113, "posy": 114.3908420701812, "radio": 30, "direccion": 282, "color": "aquamarine", "entidad": 589, "velocidad": 2, "energia": -0.19999999999941115, "descanso": -0.19999999999941115, "experiencia": 100.1999999999994, "inventario": [{"posx": 728, "posy": 260, "color": "LightGreen"}]}, {"posx": 763.8250186616193, "posy": 347.35620386100254, "radio": 30, "direccion": 337, "color": "pink", "entidad": 593, "velocidad": 2, "energia": -0.19999999999941115, "descanso": -0.19999999999941115, "experiencia": 100.1999999999994, "inventario": [{"posx": 374, "posy": 274, "color": "SteelBlue"}]}, {"posx": 250.11857895235698, "posy": 118.78909088429882, "radio": 30, "direccion": 50.1415926535898, "color": "aquamarine", "entidad": 597, "velocidad": 2, "energia": -0.19999999999941115, "descanso": -0.19999999999941115, "experiencia": 100.1999999999994, "inventario": [{"posx": 245, "posy": 243, "color": "DeepPink"}]}, {"posx": 647.5602994386071, "posy": 937.2504657117724, "radio": 30, "direccion": 25, "color": "aquamarine", "entidad": 601, "velocidad": 2, "energia": -0.19999999999941115, "descanso": -0.19999999999941115, "experiencia": 100.1999999999994, "inventario": [{"posx": 164, "posy": 464, "color": "sky blue"}]}, {"posx": 626.097798408553, "posy": 505.0264128384572, "radio": 30, "direccion": 126, "color": "LightGreen", "entidad": 605, "velocidad": 2, "energia": -0.19999999999941115, "descanso": -0.19999999999941115, "experiencia": 100.1999999999994, "inventario": [{"posx": 39, "posy": 331, "color": "aquamarine"}]}, {"posx": 921.7907573661112, "posy": 190.8838037095596, "radio": 30, "direccion": 117.1415926535898, "color": "turquoise", "entidad": 609, "velocidad": 2, "energia": -0.19999999999941115, "descanso": -0.19999999999941115, "experiencia": 100.1999999999994, "inventario": [{"posx": 520, "posy": 712, "color": "pink"}]}, {"posx": 424.0000001776334, "posy": 4.988213557836537, "radio": 30, "direccion": 355, "color": "SteelBlue", "entidad": 613, "velocidad": 2, "energia": -0.19999999999941115, "descanso": -0.19999999999941115, "experiencia": 100.1999999999994, "inventario": [{"posx": 157, "posy": 442, "color": "turquoise"}]}, {"posx": 461.67712638113284, "posy": 49.17215219754249, "radio": 30, "direccion": 142, "color": "turquoise", "entidad": 617, "velocidad": 2, "energia": -0.19999999999941115, "descanso": -0.19999999999941115, "experiencia": 100.1999999999994, "inventario": [{"posx": 208, "posy": 337, "color": "sky blue"}]}, {"posx": 316.0472907786919, "posy": 478.54713184698636, "radio": 30, "direccion": 88.1415926535898, "color": "turquoise", "entidad": 621, "velocidad": 2, "energia": -0.19999999999941115, "descanso": -0.19999999999941115, "experiencia": 100.1999999999994, "inventario": [{"posx": 984, "posy": 310, "color": "sky blue"}]}, {"posx": 559.094067398669, "posy": 505.9968431734938, "radio": 30, "direccion": 122, "color": "turquoise", "entidad": 625, "velocidad": 2, "energia": -0.19999999999941115, "descanso": -0.19999999999941115, "experiencia": 100.1999999999994, "inventario": [{"posx": 231, "posy": 616, "color": "DeepPink"}]}, {"posx": 43.21243242771062, "posy": 192.838228153153, "radio": 30, "direccion": 207.14159265358978, "color": "pink", "entidad": 629, "velocidad": 2, "energia": -0.19999999999941115, "descanso": -0.19999999999941115, "experiencia": 100.1999999999994, "inventario": [{"posx": 580, "posy": 647, "color": "violet"}]}, {"posx": 524.069970362905, "posy": 535.0290604912987, "radio": 30, "direccion": 204, "color": "LightGreen", "entidad": 633, "velocidad": 2, "energia": -0.19999999999941115, "descanso": -0.19999999999941115, "experiencia": 100.1999999999994, "inventario": [{"posx": 1016, "posy": 311, "color": "LightGreen"}]}, {"posx": 342.3514535017224, "posy": 20.797638350971106, "radio": 30, "direccion": 59.1415926535898, "color": "aquamarine", "entidad": 637, "velocidad": 2, "energia": -0.19999999999941115, "descanso": -0.19999999999941115, "experiencia": 100.1999999999994, "inventario": [{"posx": 804, "posy": 183, "color": "SteelBlue"}]}, {"posx": 452.51639260535705, "posy": 305.9372950361941, "radio": 30, "direccion": 196.14159265358978, "color": "LightGreen", "entidad": 641, "velocidad": 2, "energia": -0.19999999999941115, "descanso": -0.19999999999941115, "experiencia": 100.1999999999994, "inventario": [{"posx": 741, "posy": 418, "color": "sky blue"}]}, {"posx": 1000.4792245721876, "posy": 586.2871376726741, "radio": 30, "direccion": 89, "color": "turquoise", "entidad": 645, "velocidad": 2, "energia": -0.19999999999941115, "descanso": -0.19999999999941115, "experiencia": 100.1999999999994, "inventario": [{"posx": 735, "posy": 134, "color": "turquoise"}]}, {"posx": 86.70893375052498, "posy": 317.0573419193313, "radio": 30, "direccion": 188.14159265358978, "color": "LightGreen", "entidad": 649, "velocidad": 2, "energia": -0.19999999999941115, "descanso": -0.19999999999941115, "experiencia": 100.1999999999994, "inventario": [{"posx": 559, "posy": 984, "color": "aquamarine"}]}, {"posx": 314.18335633970446, "posy": 919.2746157555755, "radio": 30, "direccion": 342, "color": "sky blue", "entidad": 653, "velocidad": 2, "energia": -0.19999999999941115, "descanso": -0.19999999999941115, "experiencia": 100.1999999999994, "inventario": [{"posx": 495, "posy": 292, "color": "violet"}]}, {"posx": 662.0524916030355, "posy": 667.0698550897008, "radio": 30, "direccion": 47.1415926535898, "color": "turquoise", "entidad": 657, "velocidad": 2, "energia": -0.19999999999941115, "descanso": -0.19999999999941115, "experiencia": 100.1999999999994, "inventario": [{"posx": 864, "posy": 746, "color": "DeepPink"}]}, {"posx": 304.9489661534039, "posy": 450.23615046995405, "radio": 30, "direccion": 263, "color": "violet", "entidad": 661, "velocidad": 2, "energia": -0.19999999999941115, "descanso": -0.19999999999941115, "experiencia": 100.1999999999994, "inventario": [{"posx": 863, "posy": 435, "color": "LightGreen"}]}, {"posx": 532.6001965852375, "posy": 638.096824042649, "radio": 30, "direccion": 338, "color": "aquamarine", "entidad": 665, "velocidad": 2, "energia": -0.19999999999941115, "descanso": -0.19999999999941115, "experiencia": 100.1999999999994, "inventario": [{"posx": 867, "posy": 171, "color": "violet"}]}, {"posx": 514.6642619015705, "posy": 5.02128067868108, "radio": 30, "direccion": 31, "color": "LightGreen", "entidad": 669, "velocidad": 2, "energia": -0.19999999999941115, "descanso": -0.19999999999941115, "experiencia": 100.1999999999994, "inventario": [{"posx": 348, "posy": 968, "color": "pink"}]}, {"posx": 625.7869663026121, "posy": 712.5730816308387, "radio": 30, "direccion": 173, "color": "LightGreen", "entidad": 673, "velocidad": 2, "energia": -0.19999999999941115, "descanso": -0.19999999999941115, "experiencia": 100.1999999999994, "inventario": [{"posx": 68, "posy": 839, "color": "SteelBlue"}]}, {"posx": 821.4265820803008, "posy": 125.74854020422403, "radio": 30, "direccion": 6, "color": "pink", "entidad": 677, "velocidad": 2, "energia": -0.19999999999941115, "descanso": -0.19999999999941115, "experiencia": 100.1999999999994, "inventario": [{"posx": 1024, "posy": 795, "color": "pink"}]}, {"posx": 751.9468978643895, "posy": 171.199989061826, "radio": 30, "direccion": 12, "color": "SteelBlue", "entidad": 681, "velocidad": 2, "energia": -0.19999999999941115, "descanso": -0.19999999999941115, "experiencia": 100.1999999999994, "inventario": [{"posx": 297, "posy": 899, "color": "sky blue"}]}, {"posx": 651.3630702879923, "posy": 561.5837917714978, "radio": 30, "direccion": 285, "color": "LightGreen", "entidad": 685, "velocidad": 2, "energia": -0.19999999999941115, "descanso": -0.19999999999941115, "experiencia": 100.1999999999994, "inventario": [{"posx": 30, "posy": 903, "color": "LightGreen"}]}, {"posx": 714.4936383570445, "posy": 535.940616171337, "radio": 30, "direccion": 136, "color": "DeepPink", "entidad": 689, "velocidad": 2, "energia": -0.19999999999941115, "descanso": -0.19999999999941115, "experiencia": 100.1999999999994, "inventario": [{"posx": 626, "posy": 893, "color": "violet"}]}, {"posx": 771.0994566148732, "posy": 989.8127469129274, "radio": 30, "direccion": 278, "color": "turquoise", "entidad": 693, "velocidad": 2, "energia": -0.19999999999941115, "descanso": -0.19999999999941115, "experiencia": 100.1999999999994, "inventario": [{"posx": 112, "posy": 429, "color": "LightGreen"}]}, {"posx": 13.944278452601974, "posy": 373.09504724895675, "radio": 30, "direccion": 261, "color": "sky blue", "entidad": 697, "velocidad": 2, "energia": -0.19999999999941115, "descanso": -0.19999999999941115, "experiencia": 100.1999999999994, "inventario": [{"posx": 909, "posy": 901, "color": "pink"}]}, {"posx": 795.5600861690349, "posy": 946.9615930344927, "radio": 30, "direccion": 20, "color": "LightGreen", "entidad": 701, "velocidad": 2, "energia": -0.19999999999941115, "descanso": -0.19999999999941115, "experiencia": 100.1999999999994, "inventario": [{"posx": 150, "posy": 790, "color": "violet"}]}, {"posx": 288.9918255768447, "posy": 249.72557467745474, "radio": 30, "direccion": 133.14159265358978, "color": "LightGreen", "entidad": 705, "velocidad": 2, "energia": -0.19999999999941115, "descanso": -0.19999999999941115, "experiencia": 100.1999999999994, "inventario": [{"posx": 446, "posy": 462, "color": "LightGreen"}]}, {"posx": 532.1522794570961, "posy": 659.1388102982208, "radio": 30, "direccion": 334, "color": "turquoise", "entidad": 709, "velocidad": 2, "energia": -0.19999999999941115, "descanso": -0.19999999999941115, "experiencia": 100.1999999999994, "inventario": [{"posx": 871, "posy": 476, "color": "LightGreen"}]}, {"posx": 709.6026833609703, "posy": 658.9240927652842, "radio": 30, "direccion": 203, "color": "sky blue", "entidad": 713, "velocidad": 2, "energia": -0.19999999999941115, "descanso": -0.19999999999941115, "experiencia": 100.1999999999994, "inventario": [{"posx": 650, "posy": 158, "color": "DeepPink"}]}, {"posx": 491.739493769261, "posy": 52.502201060310256, "radio": 30, "direccion": 21.141592653589793, "color": "turquoise", "entidad": 717, "velocidad": 2, "energia": -0.19999999999941115, "descanso": -0.19999999999941115, "experiencia": 100.1999999999994, "inventario": [{"posx": 895, "posy": 391, "color": "SteelBlue"}]}, {"posx": 312.59053908825473, "posy": 178.79729202354068, "radio": 30, "direccion": 139.14159265358978, "color": "LightGreen", "entidad": 721, "velocidad": 2, "energia": -0.19999999999941115, "descanso": -0.19999999999941115, "experiencia": 100.1999999999994, "inventario": [{"posx": 795, "posy": 524, "color": "violet"}]}, {"posx": 302.17219897999985, "posy": 607.3829741962508, "radio": 30, "direccion": 302.1415926535898, "color": "DeepPink", "entidad": 725, "velocidad": 2, "energia": -0.19999999999941115, "descanso": -0.19999999999941115, "experiencia": 100.1999999999994, "inventario": [{"posx": 470, "posy": 630, "color": "pink"}]}, {"posx": 349.97209128893144, "posy": 187.7700530301575, "radio": 30, "direccion": 236, "color": "violet", "entidad": 729, "velocidad": 2, "energia": -0.19999999999941115, "descanso": -0.19999999999941115, "experiencia": 100.1999999999994, "inventario": [{"posx": 281, "posy": 348, "color": "DeepPink"}]}, {"posx": 284.3861884546419, "posy": 741.2289950652539, "radio": 30, "direccion": 231.14159265358978, "color": "SteelBlue", "entidad": 733, "velocidad": 2, "energia": -0.19999999999941115, "descanso": -0.19999999999941115, "experiencia": 100.1999999999994, "inventario": [{"posx": 116, "posy": 688, "color": "LightGreen"}]}, {"posx": 796.2734072590305, "posy": 344.3614589122445, "radio": 30, "direccion": 16.141592653589793, "color": "aquamarine", "entidad": 737, "velocidad": 2, "energia": -0.19999999999941115, "descanso": -0.19999999999941115, "experiencia": 100.1999999999994, "inventario": [{"posx": 98, "posy": 25, "color": "turquoise"}]}, {"posx": 492.38886462463626, "posy": 874.2118005148808, "radio": 30, "direccion": 297, "color": "aquamarine", "entidad": 741, "velocidad": 2, "energia": -0.19999999999941115, "descanso": -0.19999999999941115, "experiencia": 100.1999999999994, "inventario": [{"posx": 110, "posy": 787, "color": "violet"}]}, {"posx": 483.26673063697893, "posy": 250.5232566106563, "radio": 30, "direccion": 301, "color": "SteelBlue", "entidad": 745, "velocidad": 2, "energia": -0.19999999999941115, "descanso": -0.19999999999941115, "experiencia": 100.1999999999994, "inventario": [{"posx": 874, "posy": 648, "color": "violet"}]}, {"posx": 596.6429122788994, "posy": 903.3966032358285, "radio": 30, "direccion": 134, "color": "violet", "entidad": 749, "velocidad": 2, "energia": -0.19999999999941115, "descanso": -0.19999999999941115, "experiencia": 100.1999999999994, "inventario": [{"posx": 489, "posy": 791, "color": "aquamarine"}]}, {"posx": 206.2872315882865, "posy": 566.6874818045851, "radio": 30, "direccion": 231, "color": "LightGreen", "entidad": 753, "velocidad": 2, "energia": -0.19999999999941115, "descanso": -0.19999999999941115, "experiencia": 100.1999999999994, "inventario": [{"posx": 109, "posy": 41, "color": "aquamarine"}]}, {"posx": 403.06197032922694, "posy": 107.05447291522418, "radio": 30, "direccion": 237, "color": "SteelBlue", "entidad": 757, "velocidad": 2, "energia": -0.19999999999941115, "descanso": -0.19999999999941115, "experiencia": 100.1999999999994, "inventario": [{"posx": 995, "posy": 1001, "color": "violet"}]}, {"posx": 224.39708526276144, "posy": 219.06350184721595, "radio": 30, "direccion": 299, "color": "SteelBlue", "entidad": 761, "velocidad": 2, "energia": -0.19999999999941115, "descanso": -0.19999999999941115, "experiencia": 100.1999999999994, "inventario": [{"posx": 347, "posy": 546, "color": "sky blue"}]}, {"posx": 204.17312673258976, "posy": 55.39083756538482, "radio": 30, "direccion": 275, "color": "sky blue", "entidad": 765, "velocidad": 2, "energia": -0.19999999999941115, "descanso": -0.19999999999941115, "experiencia": 100.1999999999994, "inventario": [{"posx": 866, "posy": 578, "color": "sky blue"}]}, {"posx": 760.6562596039861, "posy": 119.79179793397708, "radio": 30, "direccion": 304.1415926535898, "color": "pink", "entidad": 769, "velocidad": 2, "energia": -0.19999999999941115, "descanso": -0.19999999999941115, "experiencia": 100.1999999999994, "inventario": [{"posx": 285, "posy": 866, "color": "LightGreen"}]}, {"posx": 577.1469299842428, "posy": 256.52981299610815, "radio": 30, "direccion": 298, "color": "sky blue", "entidad": 773, "velocidad": 2, "energia": -0.19999999999941115, "descanso": -0.19999999999941115, "experiencia": 100.1999999999994, "inventario": [{"posx": 3, "posy": 183, "color": "violet"}]}, {"posx": 188.17942275854608, "posy": 644.9656936099226, "radio": 30, "direccion": 322, "color": "turquoise", "entidad": 777, "velocidad": 2, "energia": -0.19999999999941115, "descanso": -0.19999999999941115, "experiencia": 100.1999999999994, "inventario": [{"posx": 606, "posy": 888, "color": "LightGreen"}]}, {"posx": 981.5602994386071, "posy": 429.25046571177245, "radio": 30, "direccion": 25, "color": "turquoise", "entidad": 781, "velocidad": 2, "energia": -0.19999999999941115, "descanso": -0.19999999999941115, "experiencia": 100.1999999999994, "inventario": [{"posx": 291, "posy": 144, "color": "pink"}]}, {"posx": 217.05741995799582, "posy": 305.856407785032, "radio": 30, "direccion": 353.1415926535898, "color": "turquoise", "entidad": 785, "velocidad": 2, "energia": -0.19999999999941115, "descanso": -0.19999999999941115, "experiencia": 100.1999999999994, "inventario": [{"posx": 824, "posy": 1017, "color": "sky blue"}]}, {"posx": 48.04757783169837, "posy": 14.304781911090206, "radio": 30, "direccion": 307.56637061435913, "color": "pink", "entidad": 789, "velocidad": 2, "energia": -0.19999999999941115, "descanso": -0.19999999999941115, "experiencia": 100.1999999999994, "inventario": [{"posx": 314, "posy": 674, "color": "turquoise"}]}, {"posx": 1022.9489661534127, "posy": 559.236150469954, "radio": 30, "direccion": 263, "color": "SteelBlue", "entidad": 793, "velocidad": 2, "energia": -0.19999999999941115, "descanso": -0.19999999999941115, "experiencia": 100.1999999999994, "inventario": [{"posx": 854, "posy": 776, "color": "violet"}]}, {"posx": 656.6622890496243, "posy": 186.1278219674999, "radio": 30, "direccion": 23, "color": "SteelBlue", "entidad": 797, "velocidad": 2, "energia": -0.19999999999941115, "descanso": -0.19999999999941115, "experiencia": 100.1999999999994, "inventario": [{"posx": 313, "posy": 261, "color": "aquamarine"}]}, {"posx": 623.5767114049089, "posy": 867.737223262325, "radio": 30, "direccion": 349, "color": "SteelBlue", "entidad": 801, "velocidad": 2, "energia": -0.19999999999941115, "descanso": -0.19999999999941115, "experiencia": 100.1999999999994, "inventario": [{"posx": 131, "posy": 764, "color": "pink"}]}, {"posx": 614.8788521795608, "posy": 772.8407891817204, "radio": 30, "direccion": 347, "color": "SteelBlue", "entidad": 805, "velocidad": 2, "energia": -0.19999999999941115, "descanso": -0.19999999999941115, "experiencia": 100.1999999999994, "inventario": [{"posx": 679, "posy": 335, "color": "turquoise"}]}, {"posx": 672.6218727825319, "posy": 287.3329027002309, "radio": 30, "direccion": 225, "color": "sky blue", "entidad": 809, "velocidad": 2, "energia": -0.19999999999941115, "descanso": -0.19999999999941115, "experiencia": 100.1999999999994, "inventario": [{"posx": 529, "posy": 826, "color": "violet"}]}, {"posx": 723.7437574103803, "posy": 515.4212036679381, "radio": 30, "direccion": 192.14159265358978, "color": "DeepPink", "entidad": 813, "velocidad": 2, "energia": -0.19999999999941115, "descanso": -0.19999999999941115, "experiencia": 100.1999999999994, "inventario": [{"posx": 567, "posy": 574, "color": "sky blue"}]}, {"posx": 205.2446290326945, "posy": 753.828957307153, "radio": 30, "direccion": 267, "color": "SteelBlue", "entidad": 817, "velocidad": 2, "energia": -0.19999999999941115, "descanso": -0.19999999999941115, "experiencia": 100.1999999999994, "inventario": [{"posx": 524, "posy": 545, "color": "SteelBlue"}]}, {"posx": 549.3949513290619, "posy": 700.9756866463703, "radio": 30, "direccion": 277, "color": "SteelBlue", "entidad": 821, "velocidad": 2, "energia": -0.19999999999941115, "descanso": -0.19999999999941115, "experiencia": 100.1999999999994, "inventario": [{"posx": 606, "posy": 842, "color": "SteelBlue"}]}, {"posx": 915.1414806558425, "posy": 136.80781215691775, "radio": 30, "direccion": 74, "color": "violet", "entidad": 825, "velocidad": 2, "energia": -0.19999999999941115, "descanso": -0.19999999999941115, "experiencia": 100.1999999999994, "inventario": [{"posx": 604, "posy": 816, "color": "SteelBlue"}]}, {"posx": 819.4265820803007, "posy": 303.74854020421304, "radio": 30, "direccion": 6, "color": "violet", "entidad": 829, "velocidad": 2, "energia": -0.19999999999941115, "descanso": -0.19999999999941115, "experiencia": 100.1999999999994, "inventario": [{"posx": 350, "posy": 135, "color": "turquoise"}]}, {"posx": 568.1601154225975, "posy": 426.6184569305513, "radio": 30, "direccion": 209, "color": "DeepPink", "entidad": 833, "velocidad": 2, "energia": -0.19999999999941115, "descanso": -0.19999999999941115, "experiencia": 100.1999999999994, "inventario": [{"posx": 494, "posy": 735, "color": "turquoise"}]}, {"posx": 953.4101138197586, "posy": 194.703601584964, "radio": 30, "direccion": 233.14159265358978, "color": "pink", "entidad": 837, "velocidad": 2, "energia": -0.19999999999941115, "descanso": -0.19999999999941115, "experiencia": 100.1999999999994, "inventario": [{"posx": 564, "posy": 52, "color": "violet"}]}, {"posx": 419.531684603755, "posy": 307.0827127710447, "radio": 30, "direccion": 49, "color": "pink", "entidad": 841, "velocidad": 2, "energia": -0.19999999999941115, "descanso": -0.19999999999941115, "experiencia": 100.1999999999994, "inventario": [{"posx": 878, "posy": 743, "color": "SteelBlue"}]}, {"posx": 897.4751234552066, "posy": 93.23342330449779, "radio": 30, "direccion": 22.141592653589793, "color": "pink", "entidad": 845, "velocidad": 2, "energia": -0.19999999999941115, "descanso": -0.19999999999941115, "experiencia": 100.1999999999994, "inventario": [{"posx": 124, "posy": 501, "color": "turquoise"}]}, {"posx": 824.913767778409, "posy": 817.9339114546137, "radio": 30, "direccion": 227, "color": "turquoise", "entidad": 849, "velocidad": 2, "energia": -0.19999999999941115, "descanso": -0.19999999999941115, "experiencia": 100.1999999999994, "inventario": [{"posx": 241, "posy": 814, "color": "aquamarine"}]}, {"posx": 355.32266274743233, "posy": 351.10887236852614, "radio": 30, "direccion": 190.14159265358978, "color": "DeepPink", "entidad": 853, "velocidad": 2, "energia": -0.19999999999941115, "descanso": -0.19999999999941115, "experiencia": 100.1999999999994, "inventario": [{"posx": 346, "posy": 877, "color": "LightGreen"}]}, {"posx": 43.731880552443926, "posy": 822.0087866685393, "radio": 30, "direccion": 354, "color": "LightGreen", "entidad": 857, "velocidad": 2, "energia": -0.19999999999941115, "descanso": -0.19999999999941115, "experiencia": 100.1999999999994, "inventario": [{"posx": 791, "posy": 92, "color": "pink"}]}, {"posx": 41.881849854274705, "posy": 788.2489644758109, "radio": 30, "direccion": 92.1415926535898, "color": "aquamarine", "entidad": 861, "velocidad": 2, "energia": -0.19999999999941115, "descanso": -0.19999999999941115, "experiencia": 100.1999999999994, "inventario": [{"posx": 266, "posy": 445, "color": "violet"}]}, {"posx": 33.537808043571395, "posy": 199.38335318100678, "radio": 30, "direccion": 301.1415926535898, "color": "aquamarine", "entidad": 865, "velocidad": 2, "energia": -0.19999999999941115, "descanso": -0.19999999999941115, "experiencia": 100.1999999999994, "inventario": [{"posx": 167, "posy": 740, "color": "violet"}]}, {"posx": 96.82813976606332, "posy": 469.619446690617, "radio": 30, "direccion": 146, "color": "turquoise", "entidad": 869, "velocidad": 2, "energia": -0.19999999999941115, "descanso": -0.19999999999941115, "experiencia": 100.1999999999994, "inventario": [{"posx": 965, "posy": 648, "color": "turquoise"}]}, {"posx": 311.6819226243847, "posy": 522.3761104221554, "radio": 30, "direccion": 352.1415926535898, "color": "turquoise", "entidad": 873, "velocidad": 2, "energia": -0.19999999999941115, "descanso": -0.19999999999941115, "experiencia": 100.1999999999994, "inventario": [{"posx": 816, "posy": 414, "color": "LightGreen"}]}, {"posx": 354.4941991031814, "posy": 333.9150158779622, "radio": 30, "direccion": 206, "color": "SteelBlue", "entidad": 877, "velocidad": 2, "energia": -0.19999999999941115, "descanso": -0.19999999999941115, "experiencia": 100.1999999999994, "inventario": [{"posx": 625, "posy": 491, "color": "LightGreen"}]}, {"posx": 997.152279457076, "posy": 409.13881029821573, "radio": 30, "direccion": 334, "color": "aquamarine", "entidad": 881, "velocidad": 2, "energia": -0.19999999999941115, "descanso": -0.19999999999941115, "experiencia": 100.1999999999994, "inventario": [{"posx": 996, "posy": 825, "color": "LightGreen"}]}, {"posx": 186.10873243292565, "posy": 106.15443260010088, "radio": 30, "direccion": 85, "color": "sky blue", "entidad": 885, "velocidad": 2, "energia": -0.19999999999941115, "descanso": -0.19999999999941115, "experiencia": 100.1999999999994, "inventario": [{"posx": 703, "posy": 626, "color": "LightGreen"}]}, {"posx": 933.0153999328938, "posy": 523.9740428177873, "radio": 30, "direccion": 167.14159265358978, "color": "violet", "entidad": 889, "velocidad": 2, "energia": -0.19999999999941115, "descanso": -0.19999999999941115, "experiencia": 100.1999999999994, "inventario": [{"posx": 765, "posy": 171, "color": "sky blue"}]}, {"posx": 786.001711774257, "posy": 728.32878707603, "radio": 30, "direccion": 308, "color": "pink", "entidad": 893, "velocidad": 2, "energia": -0.19999999999941115, "descanso": -0.19999999999941115, "experiencia": 100.1999999999994, "inventario": [{"posx": 994, "posy": 184, "color": "sky blue"}]}, {"posx": 914.3573829675998, "posy": 918.267997195969, "radio": 30, "direccion": 8.141592653589793, "color": "aquamarine", "entidad": 897, "velocidad": 2, "energia": -0.19999999999941115, "descanso": -0.19999999999941115, "experiencia": 100.1999999999994, "inventario": [{"posx": 747, "posy": 427, "color": "aquamarine"}]}, {"posx": 621.8050199849333, "posy": 113.24493483995566, "radio": 30, "direccion": 72, "color": "aquamarine", "entidad": 901, "velocidad": 2, "energia": -0.19999999999941115, "descanso": -0.19999999999941115, "experiencia": 100.1999999999994, "inventario": [{"posx": 237, "posy": 756, "color": "aquamarine"}]}, {"posx": 519.667411961633, "posy": 20.97240948825049, "radio": 30, "direccion": 293, "color": "turquoise", "entidad": 905, "velocidad": 2, "energia": -0.19999999999941115, "descanso": -0.19999999999941115, "experiencia": 100.1999999999994, "inventario": [{"posx": 804, "posy": 956, "color": "DeepPink"}]}, {"posx": 163.39214689742906, "posy": 3.840286826941555, "radio": 30, "direccion": 210.28318530717956, "color": "violet", "entidad": 909, "velocidad": 2, "energia": -0.19999999999941115, "descanso": -0.19999999999941115, "experiencia": 100.1999999999994, "inventario": [{"posx": 559, "posy": 763, "color": "sky blue"}]}, {"posx": 773.1091612910741, "posy": 541.1455607047128, "radio": 30, "direccion": 208, "color": "LightGreen", "entidad": 913, "velocidad": 2, "energia": -0.19999999999941115, "descanso": -0.19999999999941115, "experiencia": 100.1999999999994, "inventario": [{"posx": 432, "posy": 960, "color": "LightGreen"}]}, {"posx": 415.2833226223702, "posy": 253.73093438076714, "radio": 30, "direccion": 227.14159265358978, "color": "violet", "entidad": 917, "velocidad": 2, "energia": -0.19999999999941115, "descanso": -0.19999999999941115, "experiencia": 100.1999999999994, "inventario": [{"posx": 363, "posy": 612, "color": "aquamarine"}]}, {"posx": 222.34659661160617, "posy": 307.510587537287, "radio": 30, "direccion": 284.1415926535898, "color": "LightGreen", "entidad": 921, "velocidad": 2, "energia": -0.19999999999941115, "descanso": -0.19999999999941115, "experiencia": 100.1999999999994, "inventario": [{"posx": 767, "posy": 243, "color": "SteelBlue"}]}, {"posx": 166.0270948982082, "posy": 9.775919059861655, "radio": 30, "direccion": 203.28318530717956, "color": "pink", "entidad": 925, "velocidad": 2, "energia": -0.19999999999941115, "descanso": -0.19999999999941115, "experiencia": 100.1999999999994, "inventario": [{"posx": 328, "posy": 297, "color": "turquoise"}]}, {"posx": 713.1492547609012, "posy": 464.00187479576107, "radio": 30, "direccion": 113, "color": "aquamarine", "entidad": 929, "velocidad": 2, "energia": -0.19999999999941115, "descanso": -0.19999999999941115, "experiencia": 100.1999999999994, "inventario": [{"posx": 2, "posy": 137, "color": "LightGreen"}]}, {"posx": 1020.1822909541847, "posy": 367.0596077547598, "radio": 30, "direccion": 51, "color": "DeepPink", "entidad": 933, "velocidad": 2, "energia": -0.19999999999941115, "descanso": -0.19999999999941115, "experiencia": 100.1999999999994, "inventario": [{"posx": 87, "posy": 650, "color": "turquoise"}]}, {"posx": 782.8006582860527, "posy": 27.36110611733153, "radio": 30, "direccion": 299.1415926535898, "color": "DeepPink", "entidad": 937, "velocidad": 2, "energia": -0.19999999999941115, "descanso": -0.19999999999941115, "experiencia": 100.1999999999994, "inventario": [{"posx": 306, "posy": 53, "color": "aquamarine"}]}, {"posx": 41.56271221606529, "posy": 334.86885730245785, "radio": 30, "direccion": 317, "color": "sky blue", "entidad": 941, "velocidad": 2, "energia": -0.19999999999941115, "descanso": -0.19999999999941115, "experiencia": 100.1999999999994, "inventario": [{"posx": 160, "posy": 830, "color": "aquamarine"}]}, {"posx": -0.9846831203006052, "posy": 605.5391380674399, "radio": 30, "direccion": 22, "color": "violet", "entidad": 945, "velocidad": 2, "energia": -0.19999999999941115, "descanso": -0.19999999999941115, "experiencia": 100.1999999999994, "inventario": [{"posx": 541, "posy": 832, "color": "violet"}]}, {"posx": 558.1220202829409, "posy": 318.79938612615274, "radio": 30, "direccion": 158.14159265358978, "color": "LightGreen", "entidad": 949, "velocidad": 2, "energia": -0.19999999999941115, "descanso": -0.19999999999941115, "experiencia": 100.1999999999994, "inventario": [{"posx": 162, "posy": 182, "color": "DeepPink"}]}, {"posx": 396.96050286895104, "posy": 600.7695329691555, "radio": 30, "direccion": 312, "color": "pink", "entidad": 953, "velocidad": 2, "energia": -0.19999999999941115, "descanso": -0.19999999999941115, "experiencia": 100.1999999999994, "inventario": [{"posx": 1003, "posy": 628, "color": "aquamarine"}]}, {"posx": 974.0232992099037, "posy": 837.4019241780491, "radio": 30, "direccion": 110.1415926535898, "color": "turquoise", "entidad": 957, "velocidad": 2, "energia": -0.19999999999941115, "descanso": -0.19999999999941115, "experiencia": 100.1999999999994, "inventario": [{"posx": 963, "posy": 783, "color": "turquoise"}]}, {"posx": 438.6033257652127, "posy": 313.5271655955314, "radio": 30, "direccion": 83.1415926535898, "color": "turquoise", "entidad": 961, "velocidad": 2, "energia": -0.19999999999941115, "descanso": -0.19999999999941115, "experiencia": 100.1999999999994, "inventario": [{"posx": 301, "posy": 409, "color": "sky blue"}]}, {"posx": 117.92470660504107, "posy": 358.316805397253, "radio": 30, "direccion": 133.14159265358978, "color": "turquoise", "entidad": 965, "velocidad": 2, "energia": -0.19999999999941115, "descanso": -0.19999999999941115, "experiencia": 100.1999999999994, "inventario": [{"posx": 552, "posy": 992, "color": "turquoise"}]}, {"posx": 21.562712216065034, "posy": 526.8688573024579, "radio": 30, "direccion": 317, "color": "pink", "entidad": 969, "velocidad": 2, "energia": -0.19999999999941115, "descanso": -0.19999999999941115, "experiencia": 100.1999999999994, "inventario": [{"posx": 810, "posy": 65, "color": "LightGreen"}]}, {"posx": 219.66685992869714, "posy": 981.9730961292787, "radio": 30, "direccion": 143.14159265358978, "color": "aquamarine", "entidad": 973, "velocidad": 2, "energia": -0.19999999999941115, "descanso": -0.19999999999941115, "experiencia": 100.1999999999994, "inventario": [{"posx": 455, "posy": 986, "color": "SteelBlue"}]}, {"posx": 112.72936761277758, "posy": 337.558515812009, "radio": 30, "direccion": 196.14159265358978, "color": "SteelBlue", "entidad": 977, "velocidad": 2, "energia": -0.19999999999941115, "descanso": -0.19999999999941115, "experiencia": 100.1999999999994, "inventario": [{"posx": 766, "posy": 313, "color": "aquamarine"}]}, {"posx": 204.20108310874676, "posy": 927.142854093558, "radio": 30, "direccion": 359.1415926535898, "color": "DeepPink", "entidad": 981, "velocidad": 2, "energia": -0.19999999999941115, "descanso": -0.19999999999941115, "experiencia": 100.1999999999994, "inventario": [{"posx": 680, "posy": 950, "color": "pink"}]}, {"posx": 484.010886816769, "posy": 126.1188962151312, "radio": 30, "direccion": 230, "color": "violet", "entidad": 985, "velocidad": 2, "energia": -0.19999999999941115, "descanso": -0.19999999999941115, "experiencia": 100.1999999999994, "inventario": [{"posx": 1005, "posy": 724, "color": "DeepPink"}]}, {"posx": 194.6026833609877, "posy": 404.9240927652805, "radio": 30, "direccion": 203, "color": "violet", "entidad": 989, "velocidad": 2, "energia": -0.19999999999941115, "descanso": -0.19999999999941115, "experiencia": 100.1999999999994, "inventario": [{"posx": 71, "posy": 426, "color": "SteelBlue"}]}, {"posx": 537.7013754970422, "posy": 461.4000587320898, "radio": 30, "direccion": 305, "color": "turquoise", "entidad": 993, "velocidad": 2, "energia": -0.19999999999941115, "descanso": -0.19999999999941115, "experiencia": 100.1999999999994, "inventario": [{"posx": 868, "posy": 966, "color": "SteelBlue"}]}, {"posx": 938.4693018108603, "posy": 898.5638965826361, "radio": 30, "direccion": 220, "color": "violet", "entidad": 997, "velocidad": 2, "energia": -0.19999999999941115, "descanso": -0.19999999999941115, "experiencia": 100.1999999999994, "inventario": [{"posx": 429, "posy": 749, "color": "pink"}]}, {"posx": 910.448249992097, "posy": 653.4410906332029, "radio": 30, "direccion": 339, "color": "violet", "entidad": 1001, "velocidad": 2, "energia": -0.19999999999941115, "descanso": -0.19999999999941115, "experiencia": 100.1999999999994, "inventario": [{"posx": 58, "posy": 571, "color": "sky blue"}]}, {"posx": 359.78474128755465, "posy": 222.8813318034043, "radio": 30, "direccion": 321, "color": "LightGreen", "entidad": 1005, "velocidad": 2, "energia": -0.19999999999941115, "descanso": -0.19999999999941115, "experiencia": 100.1999999999994, "inventario": [{"posx": 798, "posy": 667, "color": "sky blue"}]}, {"posx": 806.7609184044406, "posy": 213.89651973597952, "radio": 30, "direccion": 157, "color": "sky blue", "entidad": 1009, "velocidad": 2, "energia": -0.19999999999941115, "descanso": -0.19999999999941115, "experiencia": 100.1999999999994, "inventario": [{"posx": 392, "posy": 878, "color": "turquoise"}]}, {"posx": 223.4904376907698, "posy": 318.9390381662942, "radio": 30, "direccion": 58.1415926535898, "color": "pink", "entidad": 1013, "velocidad": 2, "energia": -0.19999999999941115, "descanso": -0.19999999999941115, "experiencia": 100.1999999999994, "inventario": [{"posx": 745, "posy": 904, "color": "SteelBlue"}]}, {"posx": 865.618633803636, "posy": 248.01055678568903, "radio": 30, "direccion": 144, "color": "turquoise", "entidad": 1017, "velocidad": 2, "energia": -0.19999999999941115, "descanso": -0.19999999999941115, "experiencia": 100.1999999999994, "inventario": [{"posx": 389, "posy": 911, "color": "SteelBlue"}]}, {"posx": 844.2291828193873, "posy": 331.2568006256233, "radio": 30, "direccion": 251, "color": "pink", "entidad": 1021, "velocidad": 2, "energia": -0.19999999999941115, "descanso": -0.19999999999941115, "experiencia": 100.1999999999994, "inventario": [{"posx": 712, "posy": 945, "color": "sky blue"}]}, {"posx": 752.0156987107202, "posy": 937.5373262603023, "radio": 30, "direccion": 234, "color": "DeepPink", "entidad": 1025, "velocidad": 2, "energia": -0.19999999999941115, "descanso": -0.19999999999941115, "experiencia": 100.1999999999994, "inventario": [{"posx": 917, "posy": 499, "color": "DeepPink"}]}, {"posx": 318.50116400834884, "posy": 46.41175047261217, "radio": 30, "direccion": 208.14159265358978, "color": "violet", "entidad": 1029, "velocidad": 2, "energia": -0.19999999999941115, "descanso": -0.19999999999941115, "experiencia": 100.1999999999994, "inventario": [{"posx": 141, "posy": 399, "color": "sky blue"}]}, {"posx": 846.9703895207638, "posy": 77.32637767415542, "radio": 30, "direccion": 153.14159265358978, "color": "DeepPink", "entidad": 1033, "velocidad": 2, "energia": -0.19999999999941115, "descanso": -0.19999999999941115, "experiencia": 100.1999999999994, "inventario": [{"posx": 21, "posy": 469, "color": "violet"}]}, {"posx": 785.229221052978, "posy": 386.16008458158257, "radio": 30, "direccion": 197, "color": "pink", "entidad": 1037, "velocidad": 2, "energia": -0.19999999999941115, "descanso": -0.19999999999941115, "experiencia": 100.1999999999994, "inventario": [{"posx": 1011, "posy": 446, "color": "violet"}]}, {"posx": 476.4015581172392, "posy": 228.70240209535362, "radio": 30, "direccion": 127.1415926535898, "color": "turquoise", "entidad": 1041, "velocidad": 2, "energia": -0.19999999999941115, "descanso": -0.19999999999941115, "experiencia": 100.1999999999994, "inventario": [{"posx": 648, "posy": 611, "color": "sky blue"}]}, {"posx": 138.89461318782446, "posy": 32.601432652348265, "radio": 30, "direccion": 96.1415926535898, "color": "violet", "entidad": 1045, "velocidad": 2, "energia": -0.19999999999941115, "descanso": -0.19999999999941115, "experiencia": 100.1999999999994, "inventario": [{"posx": 293, "posy": 469, "color": "turquoise"}]}, {"posx": 52.382987318055335, "posy": 330.80143587502806, "radio": 30, "direccion": 346.1415926535898, "color": "LightGreen", "entidad": 1049, "velocidad": 2, "energia": -0.19999999999941115, "descanso": -0.19999999999941115, "experiencia": 100.1999999999994, "inventario": [{"posx": 986, "posy": 90, "color": "sky blue"}]}, {"posx": 940.4502627273024, "posy": 730.692225138485, "radio": 30, "direccion": 224.14159265358978, "color": "turquoise", "entidad": 1053, "velocidad": 2, "energia": -0.19999999999941115, "descanso": -0.19999999999941115, "experiencia": 100.1999999999994, "inventario": [{"posx": 830, "posy": 940, "color": "SteelBlue"}]}, {"posx": 163.36022186203985, "posy": 547.0954665986594, "radio": 30, "direccion": 300, "color": "DeepPink", "entidad": 1057, "velocidad": 2, "energia": -0.19999999999941115, "descanso": -0.19999999999941115, "experiencia": 100.1999999999994, "inventario": [{"posx": 507, "posy": 443, "color": "turquoise"}]}, {"posx": 783.2330654095701, "posy": 415.42004204452724, "radio": 30, "direccion": 179.14159265358978, "color": "pink", "entidad": 1061, "velocidad": 2, "energia": -0.19999999999941115, "descanso": -0.19999999999941115, "experiencia": 100.1999999999994, "inventario": [{"posx": 720, "posy": 188, "color": "turquoise"}]}, {"posx": 486.08540269209277, "posy": 669.1895916156556, "radio": 30, "direccion": 352, "color": "DeepPink", "entidad": 1065, "velocidad": 2, "energia": -0.19999999999941115, "descanso": -0.19999999999941115, "experiencia": 100.1999999999994, "inventario": [{"posx": 166, "posy": 631, "color": "sky blue"}]}, {"posx": 161.01168538692215, "posy": 783.9295200902852, "radio": 30, "direccion": 30.141592653589793, "color": "SteelBlue", "entidad": 1069, "velocidad": 2, "energia": -0.19999999999941115, "descanso": -0.19999999999941115, "experiencia": 100.1999999999994, "inventario": [{"posx": 924, "posy": 421, "color": "aquamarine"}]}, {"posx": 362.5699642337276, "posy": 188.31012783313963, "radio": 30, "direccion": 99, "color": "pink", "entidad": 1073, "velocidad": 2, "energia": -0.19999999999941115, "descanso": -0.19999999999941115, "experiencia": 100.1999999999994, "inventario": [{"posx": 780, "posy": 856, "color": "SteelBlue"}]}, {"posx": 7.849276735230227, "posy": 527.8433680677856, "radio": 30, "direccion": 174, "color": "pink", "entidad": 1077, "velocidad": 2, "energia": -0.19999999999941115, "descanso": -0.19999999999941115, "experiencia": 100.1999999999994, "inventario": [{"posx": 312, "posy": 545, "color": "aquamarine"}]}, {"posx": 57.88366010590511, "posy": 892.1362125563618, "radio": 30, "direccion": 147, "color": "SteelBlue", "entidad": 1081, "velocidad": 2, "energia": -0.19999999999941115, "descanso": -0.19999999999941115, "experiencia": 100.1999999999994, "inventario": [{"posx": 845, "posy": 766, "color": "LightGreen"}]}, {"posx": 201.9053136766662, "posy": 649.8252427852951, "radio": 30, "direccion": 174.14159265358978, "color": "SteelBlue", "entidad": 1085, "velocidad": 2, "energia": -0.19999999999941115, "descanso": -0.19999999999941115, "experiencia": 100.1999999999994, "inventario": [{"posx": 867, "posy": 954, "color": "pink"}]}, {"posx": 908.5890990342697, "posy": 110.03144619358754, "radio": 30, "direccion": 120.1415926535898, "color": "DeepPink", "entidad": 1089, "velocidad": 2, "energia": -0.19999999999941115, "descanso": -0.19999999999941115, "experiencia": 100.1999999999994, "inventario": [{"posx": 517, "posy": 428, "color": "DeepPink"}]}, {"posx": 644.0493008945547, "posy": 453.776075632226, "radio": 30, "direccion": 43, "color": "LightGreen", "entidad": 1093, "velocidad": 2, "energia": -0.19999999999941115, "descanso": -0.19999999999941115, "experiencia": 100.1999999999994, "inventario": [{"posx": 951, "posy": 175, "color": "pink"}]}, {"posx": 851.6001965852375, "posy": 306.096824042649, "radio": 30, "direccion": 338, "color": "sky blue", "entidad": 1097, "velocidad": 2, "energia": -0.19999999999941115, "descanso": -0.19999999999941115, "experiencia": 100.1999999999994, "inventario": [{"posx": 343, "posy": 321, "color": "pink"}]}, {"posx": 200.45021378489716, "posy": 623.1376070208545, "radio": 30, "direccion": 177, "color": "aquamarine", "entidad": 1101, "velocidad": 2, "energia": -0.19999999999941115, "descanso": -0.19999999999941115, "experiencia": 100.1999999999994, "inventario": [{"posx": 158, "posy": 997, "color": "LightGreen"}]}, {"posx": 173.45812497854405, "posy": 308.21910215812244, "radio": 30, "direccion": 192, "color": "turquoise", "entidad": 1105, "velocidad": 2, "energia": -0.19999999999941115, "descanso": -0.19999999999941115, "experiencia": 100.1999999999994, "inventario": [{"posx": 557, "posy": 998, "color": "LightGreen"}]}, {"posx": 403.79642783060604, "posy": 237.45283713044407, "radio": 30, "direccion": 264, "color": "turquoise", "entidad": 1109, "velocidad": 2, "energia": -0.19999999999941115, "descanso": -0.19999999999941115, "experiencia": 100.1999999999994, "inventario": [{"posx": 18, "posy": 956, "color": "sky blue"}]}, {"posx": 295.97094749697015, "posy": 464.6043376108386, "radio": 30, "direccion": 309, "color": "LightGreen", "entidad": 1113, "velocidad": 2, "energia": -0.19999999999941115, "descanso": -0.19999999999941115, "experiencia": 100.1999999999994, "inventario": [{"posx": 923, "posy": 88, "color": "SteelBlue"}]}, {"posx": 895.4684748865042, "posy": 508.8067751856764, "radio": 30, "direccion": 195, "color": "aquamarine", "entidad": 1117, "velocidad": 2, "energia": -0.19999999999941115, "descanso": -0.19999999999941115, "experiencia": 100.1999999999994, "inventario": [{"posx": 867, "posy": 193, "color": "DeepPink"}]}, {"posx": 640.0303092128207, "posy": 474.2714994035486, "radio": 30, "direccion": 340, "color": "turquoise", "entidad": 1121, "velocidad": 2, "energia": -0.19999999999941115, "descanso": -0.19999999999941115, "experiencia": 100.1999999999994, "inventario": [{"posx": 34, "posy": 609, "color": "SteelBlue"}]}, {"posx": 968.8382805805786, "posy": 899.5021534101732, "radio": 30, "direccion": 149.14159265358978, "color": "SteelBlue", "entidad": 1125, "velocidad": 2, "energia": -0.19999999999941115, "descanso": -0.19999999999941115, "experiencia": 100.1999999999994, "inventario": [{"posx": 255, "posy": 583, "color": "sky blue"}]}, {"posx": 419.1486471731104, "posy": 130.38216485706272, "radio": 30, "direccion": 73, "color": "aquamarine", "entidad": 1129, "velocidad": 2, "energia": -0.19999999999941115, "descanso": -0.19999999999941115, "experiencia": 100.1999999999994, "inventario": [{"posx": 177, "posy": 400, "color": "turquoise"}]}, {"posx": 715.7568216681809, "posy": 185.0513108613906, "radio": 30, "direccion": 296.1415926535898, "color": "pink", "entidad": 1133, "velocidad": 2, "energia": -0.19999999999941115, "descanso": -0.19999999999941115, "experiencia": 100.1999999999994, "inventario": [{"posx": 487, "posy": 741, "color": "aquamarine"}]}, {"posx": 988.634373287606, "posy": 436.1928658267496, "radio": 30, "direccion": 17.141592653589793, "color": "sky blue", "entidad": 1137, "velocidad": 2, "energia": -0.19999999999941115, "descanso": -0.19999999999941115, "experiencia": 100.1999999999994, "inventario": [{"posx": 740, "posy": 437, "color": "aquamarine"}]}, {"posx": 197.65866460862927, "posy": 114.47684826772434, "radio": 30, "direccion": 137, "color": "LightGreen", "entidad": 1141, "velocidad": 2, "energia": -0.19999999999941115, "descanso": -0.19999999999941115, "experiencia": 100.1999999999994, "inventario": [{"posx": 269, "posy": 232, "color": "turquoise"}]}, {"posx": 218.67244264457076, "posy": 146.15132158864017, "radio": 30, "direccion": 332.1415926535898, "color": "pink", "entidad": 1145, "velocidad": 2, "energia": -0.19999999999941115, "descanso": -0.19999999999941115, "experiencia": 100.1999999999994, "inventario": [{"posx": 743, "posy": 376, "color": "pink"}]}, {"posx": 1017.9575403959614, "posy": 804.4183742174198, "radio": 30, "direccion": 59.1415926535898, "color": "LightGreen", "entidad": 1149, "velocidad": 2, "energia": -0.19999999999941115, "descanso": -0.19999999999941115, "experiencia": 100.1999999999994, "inventario": [{"posx": 413, "posy": 232, "color": "LightGreen"}]}, {"posx": 481.61453954456135, "posy": 881.3634674908114, "radio": 30, "direccion": 226, "color": "aquamarine", "entidad": 1153, "velocidad": 2, "energia": -0.19999999999941115, "descanso": -0.19999999999941115, "experiencia": 100.1999999999994, "inventario": [{"posx": 498, "posy": 339, "color": "SteelBlue"}]}, {"posx": 499.6145395445608, "posy": 343.36346749083367, "radio": 30, "direccion": 226, "color": "sky blue", "entidad": 1157, "velocidad": 2, "energia": -0.19999999999941115, "descanso": -0.19999999999941115, "experiencia": 100.1999999999994, "inventario": [{"posx": 109, "posy": 412, "color": "violet"}]}, {"posx": 90.84062546977432, "posy": 614.8843478161357, "radio": 30, "direccion": 13.141592653589793, "color": "DeepPink", "entidad": 1161, "velocidad": 2, "energia": -0.19999999999941115, "descanso": -0.19999999999941115, "experiencia": 100.1999999999994, "inventario": [{"posx": 838, "posy": 679, "color": "turquoise"}]}, {"posx": 737.5282795385842, "posy": 284.64628632546794, "radio": 30, "direccion": 212, "color": "DeepPink", "entidad": 1165, "velocidad": 2, "energia": -0.19999999999941115, "descanso": -0.19999999999941115, "experiencia": 100.1999999999994, "inventario": [{"posx": 973, "posy": 71, "color": "aquamarine"}]}, {"posx": 984.4047464623667, "posy": 201.37738055490772, "radio": 30, "direccion": 75, "color": "turquoise", "entidad": 1169, "velocidad": 2, "energia": -0.19999999999941115, "descanso": -0.19999999999941115, "experiencia": 100.1999999999994, "inventario": [{"posx": 9, "posy": 796, "color": "pink"}]}, {"posx": 289.7304479133237, "posy": 154.00382923867403, "radio": 30, "direccion": 11, "color": "violet", "entidad": 1173, "velocidad": 2, "energia": -0.19999999999941115, "descanso": -0.19999999999941115, "experiencia": 100.1999999999994, "inventario": [{"posx": 874, "posy": 877, "color": "SteelBlue"}]}, {"posx": 231.95143059106695, "posy": 421.80673372109334, "radio": 30, "direccion": 53, "color": "turquoise", "entidad": 1177, "velocidad": 2, "energia": -0.19999999999941115, "descanso": -0.19999999999941115, "experiencia": 100.1999999999994, "inventario": [{"posx": 723, "posy": 865, "color": "sky blue"}]}, {"posx": 995.5835057110061, "posy": 773.601988978201, "radio": 30, "direccion": 19, "color": "DeepPink", "entidad": 1181, "velocidad": 2, "energia": -0.19999999999941115, "descanso": -0.19999999999941115, "experiencia": 100.1999999999994, "inventario": [{"posx": 503, "posy": 395, "color": "violet"}]}, {"posx": 1023.2136741669296, "posy": 995.3786910513804, "radio": 30, "direccion": 54.1415926535898, "color": "DeepPink", "entidad": 1185, "velocidad": 2, "energia": -0.19999999999941115, "descanso": -0.19999999999941115, "experiencia": 100.1999999999994, "inventario": [{"posx": 848, "posy": 210, "color": "turquoise"}]}, {"posx": 321.2582015944438, "posy": 947.0151550598772, "radio": 30, "direccion": 1, "color": "LightGreen", "entidad": 1189, "velocidad": 2, "energia": -0.19999999999941115, "descanso": -0.19999999999941115, "experiencia": 100.1999999999994, "inventario": [{"posx": 419, "posy": 451, "color": "aquamarine"}]}, {"posx": 802.9709474969479, "posy": 696.604337610827, "radio": 30, "direccion": 309, "color": "DeepPink", "entidad": 1193, "velocidad": 2, "energia": -0.19999999999941115, "descanso": -0.19999999999941115, "experiencia": 100.1999999999994, "inventario": [{"posx": 80, "posy": 735, "color": "SteelBlue"}]}, {"posx": 51.48897234238823, "posy": 830.0401172238786, "radio": 30, "direccion": 55.1415926535898, "color": "violet", "entidad": 1197, "velocidad": 2, "energia": -0.19999999999941115, "descanso": -0.19999999999941115, "experiencia": 100.1999999999994, "inventario": [{"posx": 905, "posy": 702, "color": "turquoise"}]}]